[{"name": "\u5c0f\u5b9d\u5bfb\u82b1\u5927\u795e\u5e26\u4f60\u627e\u5916\u56f4\u59b9\uff0c\u767d\u8863\u989c\u503c\u7f8e\u5973\u5750\u5728\u8eab\u4e0a\u634f\u5976\u5b50\uff0c\u53e3\u4ea4\u8214\u5c4c\u6d3b\u4e0d\u9519\uff0c\u4e0a\u4f4d\u9a91\u4e58\u6253\u6869\u62bd\u63d2\u731b\u64cd", "size": 136619448, "link": "https://streamtape.com/e/ZP0DmkvVDoHqpP2", "created_at": "2022\u5e7403\u670812\u65e5 18:02:39", "downloads": 0, "linkid": "ZP0DmkvVDoHqpP2", "convert": "converted", "achorname": "\u4e38\u5b50\u5466", "subscribe": "128.6\u4e07\u4f4d\u8ba2\u9605\u8005", "avatar-img": "https://huyaimg.msstatic.com/avatar/1022/07/ec5fef7c7662720286fbbb12395390_180_135.jpg?1628178596?457957", "folderName": "\u5c0f\u5b9d\u5bfb\u82b1\u5927\u795e\u5e26\u4f60\u627e\u5916\u56f4\u59b9\uff0c\u767d\u8863\u989c\u503c\u7f8e\u5973\u5750\u5728\u8eab\u4e0a\u634f\u5976\u5b50\uff0c\u53e3\u4ea4\u8214\u5c4c\u6d3b\u4e0d\u9519\uff0c\u4e0a\u4f4d\u9a91\u4e58\u6253\u6869\u62bd\u63d2\u731b\u64cd", "tags": ["\u5c0f\u5b9d", "\u5bfb\u82b1", "\u5927\u795e", "\u5e26", "\u4f60", "\u627e", "\u5916\u56f4", "\u59b9", "\uff0c", "\u767d\u8863", "\u989c\u503c", "\u7f8e\u5973", "\u5750\u5728", "\u8eab\u4e0a", "\u634f", "\u5976\u5b50", "\uff0c", "\u53e3\u4ea4", "\u8214", "\u5c4c", "\u6d3b", "\u4e0d\u9519", "\uff0c", "\u4e0a\u4f4d", "\u9a91\u4e58", "\u6253\u6869", "\u62bd\u63d2", "\u731b\u64cd"], "thumbUrl": "https://thumb.tapecontent.net/thumb/ZP0DmkvVDoHqpP2/W3w8G07wxQCeLq.jpg"}, {"name": "\u5c0f\u5b9d\u5bfb\u82b1\u7ea6\u4e86\u4e2a\u9ed1\u88e4\u59b9\u5b50\u556a\u556a\uff0c\u5750\u5728\u8eab\u4e0a\u820c\u543b\u53e3\u4ea4\u62bd\u63d2\u731b\u64cd", "size": 121648699, "link": "https://streamtape.com/e/bev4VzlRxzFLDd", "created_at": "2022\u5e7403\u670813\u65e5 04:36:52", "downloads": 0, "linkid": "bev4VzlRxzFLDd", "convert": "converted", "achorname": "\u4e38\u5b50\u5466", "subscribe": "128.6\u4e07\u4f4d\u8ba2\u9605\u8005", "avatar-img": "https://huyaimg.msstatic.com/avatar/1022/07/ec5fef7c7662720286fbbb12395390_180_135.jpg?1628178596?457957", "folderName": "\u5c0f\u5b9d\u5bfb\u82b1\u7ea6\u4e86\u4e2a\u9ed1\u88e4\u59b9\u5b50\u556a\u556a\uff0c\u5750\u5728\u8eab\u4e0a\u820c\u543b\u53e3\u4ea4\u62bd\u63d2\u731b\u64cd", "tags": ["\u5c0f\u5b9d", "\u5bfb\u82b1", "\u7ea6", "\u4e86", "\u4e2a", "\u9ed1\u88e4", "\u59b9\u5b50", "\u556a\u556a", "\uff0c", "\u5750\u5728", "\u8eab\u4e0a", "\u820c\u543b", "\u53e3\u4ea4", "\u62bd\u63d2", "\u731b\u64cd"], "thumbUrl": "https://thumb.tapecontent.net/thumb/bev4VzlRxzFLDd/4qGbA03wJliKKdo.jpg"}, {"name": "\u5c0f\u5b9d\u5bfb\u82b1\u7ea6\u4e86\u4e2a\u6781\u54c1\u989c\u503c\u767d\u8863\u7f8e\u4e73\u59b9\u5b50\uff0c\u8214\u5f04\u62bd\u63d2\u731b\u64cd\u4e0a\u4f4d\u9a91\u4e58\u547b\u541f", "size": 183647264, "link": "https://streamtape.com/e/3GK1zMvpAxHdgMB", "created_at": "2022\u5e7403\u670813\u65e5 05:42:46", "downloads": 0, "linkid": "3GK1zMvpAxHdgMB", "convert": "converted", "achorname": "\u4e38\u5b50\u5466", "subscribe": "128.6\u4e07\u4f4d\u8ba2\u9605\u8005", "avatar-img": "https://huyaimg.msstatic.com/avatar/1022/07/ec5fef7c7662720286fbbb12395390_180_135.jpg?1628178596?457957", "folderName": "\u5c0f\u5b9d\u5bfb\u82b1\u7ea6\u4e86\u4e2a\u6781\u54c1\u989c\u503c\u767d\u8863\u7f8e\u4e73\u59b9\u5b50\uff0c\u8214\u5f04\u62bd\u63d2\u731b\u64cd\u4e0a\u4f4d\u9a91\u4e58\u547b\u541f", "tags": ["\u5c0f\u5b9d", "\u5bfb\u82b1", "\u7ea6", "\u4e86", "\u4e2a", "\u6781\u54c1", "\u989c\u503c", "\u767d\u8863", "\u7f8e\u4e73", "\u59b9\u5b50", "\uff0c", "\u8214", "\u5f04", "\u62bd\u63d2", "\u731b\u64cd", "\u4e0a\u4f4d", "\u9a91\u4e58", "\u547b\u541f"], "thumbUrl": "https://thumb.tapecontent.net/thumb/3GK1zMvpAxHdgMB/3xYloMB3LGCd7ex.jpg"}, {"name": "\u5c0f\u5b9d\u5bfb\u82b1\u7ea6\u4e86\u4e2a\u957f\u76f8\u751c\u7f8e\u9ad8\u989c\u503c\u767d\u8863\u59b9\u5b50\uff0c\u5750\u5728\u8eab\u4e0a\u820c\u543b\u8c03\u60c5\u53e3\u4ea4\u62bd\u63d2\u731b\u64cd\u547b\u541f", "size": 176437172, "link": "https://streamtape.com/e/7YGgk7d6LDCRA8", "created_at": "2022\u5e7403\u670813\u65e5 05:54:35", "downloads": 0, "linkid": "7YGgk7d6LDCRA8", "convert": "converted", "achorname": "\u4e38\u5b50\u5466", "subscribe": "128.6\u4e07\u4f4d\u8ba2\u9605\u8005", "avatar-img": "https://huyaimg.msstatic.com/avatar/1022/07/ec5fef7c7662720286fbbb12395390_180_135.jpg?1628178596?457957", "folderName": "\u5c0f\u5b9d\u5bfb\u82b1\u7ea6\u4e86\u4e2a\u957f\u76f8\u751c\u7f8e\u9ad8\u989c\u503c\u767d\u8863\u59b9\u5b50\uff0c\u5750\u5728\u8eab\u4e0a\u820c\u543b\u8c03\u60c5\u53e3\u4ea4\u62bd\u63d2\u731b\u64cd\u547b\u541f", "tags": ["\u5c0f\u5b9d", "\u5bfb\u82b1", "\u7ea6", "\u4e86", "\u4e2a", "\u957f\u76f8", "\u751c\u7f8e", "\u9ad8\u989c\u503c", "\u767d\u8863", "\u59b9\u5b50", "\uff0c", "\u5750\u5728", "\u8eab\u4e0a", "\u820c\u543b", "\u8c03\u60c5", "\u53e3\u4ea4", "\u62bd\u63d2", "\u731b\u64cd", "\u547b\u541f"], "thumbUrl": "https://thumb.tapecontent.net/thumb/7YGgk7d6LDCRA8/J2LZpW6mDKCjzdP.jpg"}, {"name": "\u5c0f\u5b9d\u5bfb\u82b1\u957f\u76f8\u751c\u7f8e\u767d\u88e4\u5927\u5976\u5916\u56f4\u59b9\uff0c\u955c\u5934\u7279\u5199\u6df1\u5589\u53e3\u4ea4\uff0c\u6276\u7740\u5c0f\u8170\u540e\u5165\u62bd\u63d2\u731b\u64cd\uff0c\u9a91\u4e58\u6253\u6869\u64cd\u7684\u59b9\u5b50\u53d7\u4e0d\u4e86", "size": 175318010, "link": "https://streamtape.com/e/P7qJZGP2YVS0ddR", "created_at": "2022\u5e7403\u670813\u65e5 09:07:29", "downloads": 0, "linkid": "P7qJZGP2YVS0ddR", "convert": "converted", "achorname": "\u4e38\u5b50\u5466", "subscribe": "128.6\u4e07\u4f4d\u8ba2\u9605\u8005", "avatar-img": "https://huyaimg.msstatic.com/avatar/1022/07/ec5fef7c7662720286fbbb12395390_180_135.jpg?1628178596?457957", "folderName": "\u5c0f\u5b9d\u5bfb\u82b1\u957f\u76f8\u751c\u7f8e\u767d\u88e4\u5927\u5976\u5916\u56f4\u59b9\uff0c\u955c\u5934\u7279\u5199\u6df1\u5589\u53e3\u4ea4\uff0c\u6276\u7740\u5c0f\u8170\u540e\u5165\u62bd\u63d2\u731b\u64cd\uff0c\u9a91\u4e58\u6253\u6869\u64cd\u7684\u59b9\u5b50\u53d7\u4e0d\u4e86", "tags": ["\u5c0f\u5b9d", "\u5bfb\u82b1", "\u957f\u76f8", "\u751c\u7f8e", "\u767d\u88e4", "\u5927\u5976", "\u5916\u56f4", "\u59b9", "\uff0c", "\u955c\u5934", "\u7279\u5199", "\u6df1\u5589", "\u53e3\u4ea4", "\uff0c", "\u6276", "\u7740", "\u5c0f", "\u8170", "\u540e\u5165", "\u62bd\u63d2", "\u731b\u64cd", "\uff0c", "\u9a91\u4e58", "\u6253\u6869", "\u64cd", "\u7684", "\u59b9\u5b50", "\u53d7\u4e0d\u4e86"], "thumbUrl": "https://thumb.tapecontent.net/thumb/P7qJZGP2YVS0ddR/3JvMoZYXzKHdJLx.jpg"}, {"name": "\u5c0f\u5b9d\u5bfb\u82b1\u7ea6\u4e86\u4e2a\u9ad8\u989c\u503c\u751c\u7f8e\u59b9\u5b50\uff0c\u5750\u5728\u8eab\u4e0a\u820c\u543b\u6478\u5976\u955c\u5934\u524d\u53e3\u4ea4\uff0c\u4e0a\u4f4d\u9a91\u4e58\u731b\u64cd\u547b\u541f", "size": 202275022, "link": "https://streamtape.com/e/gqLJRoBDXkigp9", "created_at": "2022\u5e7403\u670813\u65e5 08:09:52", "downloads": 0, "linkid": "gqLJRoBDXkigp9", "convert": "converted", "achorname": "\u4e38\u5b50\u5466", "subscribe": "128.6\u4e07\u4f4d\u8ba2\u9605\u8005", "avatar-img": "https://huyaimg.msstatic.com/avatar/1022/07/ec5fef7c7662720286fbbb12395390_180_135.jpg?1628178596?457957", "folderName": "\u5c0f\u5b9d\u5bfb\u82b1\u7ea6\u4e86\u4e2a\u9ad8\u989c\u503c\u751c\u7f8e\u59b9\u5b50\uff0c\u5750\u5728\u8eab\u4e0a\u820c\u543b\u6478\u5976\u955c\u5934\u524d\u53e3\u4ea4\uff0c\u4e0a\u4f4d\u9a91\u4e58\u731b\u64cd\u547b\u541f", "tags": ["\u5c0f\u5b9d", "\u5bfb\u82b1", "\u7ea6", "\u4e86", "\u4e2a", "\u9ad8\u989c\u503c", "\u751c\u7f8e", "\u59b9\u5b50", "\uff0c", "\u5750\u5728", "\u8eab\u4e0a", "\u820c\u543b", "\u6478\u5976", "\u955c\u5934", "\u524d", "\u53e3\u4ea4", "\uff0c", "\u4e0a\u4f4d", "\u9a91\u4e58", "\u731b\u64cd", "\u547b\u541f"], "thumbUrl": "https://thumb.tapecontent.net/thumb/gqLJRoBDXkigp9/kDLG3e7qqJcY9w.jpg"}, {"name": "\u5c0f\u5b9d\u5bfb\u82b1\u7ea6\u4e86\u4e2a\u989c\u503c\u4e0d\u9519\u8089\u8089\u8eab\u6750\u59b9\u5b50\u556a\u556a\uff0c\u53e3\u4ea4\u8214\u5f04\u4e0a\u4f4d\u9a91\u5750\u540e\u5165\u62bd\u63d2\u5927\u529b\u731b\u64cd", "size": 241611664, "link": "https://streamtape.com/e/Ge8xB6qvRyH13Yw", "created_at": "2022\u5e7403\u670813\u65e5 04:19:05", "downloads": 0, "linkid": "Ge8xB6qvRyH13Yw", "convert": "converted", "achorname": "\u4e38\u5b50\u5466", "subscribe": "128.6\u4e07\u4f4d\u8ba2\u9605\u8005", "avatar-img": "https://huyaimg.msstatic.com/avatar/1022/07/ec5fef7c7662720286fbbb12395390_180_135.jpg?1628178596?457957", "folderName": "\u5c0f\u5b9d\u5bfb\u82b1\u7ea6\u4e86\u4e2a\u989c\u503c\u4e0d\u9519\u8089\u8089\u8eab\u6750\u59b9\u5b50\u556a\u556a\uff0c\u53e3\u4ea4\u8214\u5f04\u4e0a\u4f4d\u9a91\u5750\u540e\u5165\u62bd\u63d2\u5927\u529b\u731b\u64cd", "tags": ["\u5c0f\u5b9d", "\u5bfb\u82b1", "\u7ea6", "\u4e86", "\u4e2a", "\u989c\u503c", "\u4e0d\u9519", "\u8089\u8089", "\u8eab\u6750", "\u59b9\u5b50", "\u556a\u556a", "\uff0c", "\u53e3\u4ea4", "\u8214", "\u5f04", "\u4e0a\u4f4d", "\u9a91\u5750", "\u540e\u5165", "\u62bd\u63d2", "\u5927\u529b", "\u731b\u64cd"], "thumbUrl": "https://thumb.tapecontent.net/thumb/Ge8xB6qvRyH13Yw/vQDpPDlXRmu4R6M.jpg"}, {"name": "\u5c0f\u5b9d\u5bfb\u82b1\u7ea6\u4e86\u4e2a\u989c\u503c\u4e0d\u9519LV\u5305\u5305\u59b9\u5b50\u556a\u556a\uff0c\u8fd1\u8ddd\u79bb\u7279\u5199\u53e3\u4ea4\u540e\u5165\u5927\u529b\u62bd\u63d2\u731b\u64cd", "size": 168427310, "link": "https://streamtape.com/e/RwPM4XDlLLTd441", "created_at": "2022\u5e7403\u670813\u65e5 04:23:33", "downloads": 0, "linkid": "RwPM4XDlLLTd441", "convert": "converted", "achorname": "\u4e38\u5b50\u5466", "subscribe": "128.6\u4e07\u4f4d\u8ba2\u9605\u8005", "avatar-img": "https://huyaimg.msstatic.com/avatar/1022/07/ec5fef7c7662720286fbbb12395390_180_135.jpg?1628178596?457957", "folderName": "\u5c0f\u5b9d\u5bfb\u82b1\u7ea6\u4e86\u4e2a\u989c\u503c\u4e0d\u9519LV\u5305\u5305\u59b9\u5b50\u556a\u556a\uff0c\u8fd1\u8ddd\u79bb\u7279\u5199\u53e3\u4ea4\u540e\u5165\u5927\u529b\u62bd\u63d2\u731b\u64cd", "tags": ["\u5c0f\u5b9d", "\u5bfb\u82b1", "\u7ea6", "\u4e86", "\u4e2a", "\u989c\u503c", "\u4e0d\u9519", "LV", "\u5305\u5305", "\u59b9\u5b50", "\u556a\u556a", "\uff0c", "\u8fd1\u8ddd\u79bb", "\u7279\u5199", "\u53e3\u4ea4", "\u540e\u5165", "\u5927\u529b", "\u62bd\u63d2", "\u731b\u64cd"], "thumbUrl": "https://thumb.tapecontent.net/thumb/RwPM4XDlLLTd441/dZRkVrB1WDckWJ7.jpg"}, {"name": "\u5c0f\u5b9d\u5bfb\u82b1\u4eca\u665a\u7ea6\u4e86\u4e2a\u6781\u54c1\u6027\u611f\u7f8e\u5973\u556a\u556a\uff0c\u820c\u543b\u5750\u5728\u8eab\u4e0a\u6478\u5c41\u80a1\u53e3\u4ea4\u4e0a\u4f4d\u9a91\u4e58\u731b\u64cd", "size": 149920065, "link": "https://streamtape.com/e/ZXA6Y9AlzPho6y", "created_at": "2022\u5e7403\u670813\u65e5 05:45:56", "downloads": 0, "linkid": "ZXA6Y9AlzPho6y", "convert": "converted", "achorname": "\u4e38\u5b50\u5466", "subscribe": "128.6\u4e07\u4f4d\u8ba2\u9605\u8005", "avatar-img": "https://huyaimg.msstatic.com/avatar/1022/07/ec5fef7c7662720286fbbb12395390_180_135.jpg?1628178596?457957", "folderName": "\u5c0f\u5b9d\u5bfb\u82b1\u4eca\u665a\u7ea6\u4e86\u4e2a\u6781\u54c1\u6027\u611f\u7f8e\u5973\u556a\u556a\uff0c\u820c\u543b\u5750\u5728\u8eab\u4e0a\u6478\u5c41\u80a1\u53e3\u4ea4\u4e0a\u4f4d\u9a91\u4e58\u731b\u64cd", "tags": ["\u5c0f\u5b9d", "\u5bfb\u82b1", "\u4eca\u665a", "\u7ea6", "\u4e86", "\u4e2a", "\u6781\u54c1", "\u6027\u611f", "\u7f8e\u5973", "\u556a\u556a", "\uff0c", "\u820c\u543b", "\u5750\u5728", "\u8eab\u4e0a", "\u6478", "\u5c41\u80a1", "\u53e3", "\u4ea4\u4e0a", "\u4f4d", "\u9a91\u4e58", "\u731b\u64cd"], "thumbUrl": "https://thumb.tapecontent.net/thumb/ZXA6Y9AlzPho6y/2PK2VQrz6ouPR9.jpg"}, {"name": "\u5c0f\u5b9d\u5bfb\u82b1\u5927\u795e\u63a2\u82b1\u9ad8\u7d20\u8d28\u5927\u5708\u5916\u56f4\u59b9\uff0c\u957f\u76f8\u751c\u7f8e\u8131\u6389\u5185\u88e4\u5750\u5728\u8eab\u4e0a\u820c\u543b\u8c03\u60c5\uff0c\u7279\u5199\u62bd\u63d2\u731b\u64cd\u4e0a\u4f4d\u9a91\u4e58\u540e\u5165\u649e\u51fb", "size": 143758603, "link": "https://streamtape.com/e/ApV0v4KyXohDDK", "created_at": "2022\u5e7403\u670813\u65e5 09:30:24", "downloads": 0, "linkid": "ApV0v4KyXohDDK", "convert": "converted", "achorname": "\u4e38\u5b50\u5466", "subscribe": "128.6\u4e07\u4f4d\u8ba2\u9605\u8005", "avatar-img": "https://huyaimg.msstatic.com/avatar/1022/07/ec5fef7c7662720286fbbb12395390_180_135.jpg?1628178596?457957", "folderName": "\u5c0f\u5b9d\u5bfb\u82b1\u5927\u795e\u63a2\u82b1\u9ad8\u7d20\u8d28\u5927\u5708\u5916\u56f4\u59b9\uff0c\u957f\u76f8\u751c\u7f8e\u8131\u6389\u5185\u88e4\u5750\u5728\u8eab\u4e0a\u820c\u543b\u8c03\u60c5\uff0c\u7279\u5199\u62bd\u63d2\u731b\u64cd\u4e0a\u4f4d\u9a91\u4e58\u540e\u5165\u649e\u51fb", "tags": ["\u5c0f\u5b9d", "\u5bfb\u82b1", "\u5927\u795e", "\u63a2\u82b1", "\u9ad8\u7d20\u8d28", "\u5927", "\u5708", "\u5916\u56f4", "\u59b9", "\uff0c", "\u957f\u76f8", "\u751c\u7f8e", "\u8131\u6389", "\u5185\u88e4", "\u5750\u5728", "\u8eab\u4e0a", "\u820c\u543b", "\u8c03\u60c5", "\uff0c", "\u7279\u5199", "\u62bd\u63d2", "\u731b\u64cd", "\u4e0a\u4f4d", "\u9a91\u4e58", "\u540e\u5165", "\u649e\u51fb"], "thumbUrl": "https://thumb.tapecontent.net/thumb/ApV0v4KyXohDDK/We6rZvAb9AFb7oP.jpg"}, {"name": "\u5c0f\u5b9d\u5bfb\u82b1\u7ea6\u4e86\u4e2a\u725b\u4ed4\u88e4\u767d\u8863\u59b9\u5b50\u556a\u556a\uff0c\u53e3\u4ea4\u8214\u5f04\u4e0a\u4f4d\u9a91\u4e58\u540e\u5165\u62bd\u63d2\u5927\u529b\u731b\u64cd", "size": 191650199, "link": "https://streamtape.com/e/aRqpGgPvYOux3Yk", "created_at": "2022\u5e7403\u670813\u65e5 04:34:20", "downloads": 0, "linkid": "aRqpGgPvYOux3Yk", "convert": "converted", "achorname": "\u4e38\u5b50\u5466", "subscribe": "128.6\u4e07\u4f4d\u8ba2\u9605\u8005", "avatar-img": "https://huyaimg.msstatic.com/avatar/1022/07/ec5fef7c7662720286fbbb12395390_180_135.jpg?1628178596?457957", "folderName": "\u5c0f\u5b9d\u5bfb\u82b1\u7ea6\u4e86\u4e2a\u725b\u4ed4\u88e4\u767d\u8863\u59b9\u5b50\u556a\u556a\uff0c\u53e3\u4ea4\u8214\u5f04\u4e0a\u4f4d\u9a91\u4e58\u540e\u5165\u62bd\u63d2\u5927\u529b\u731b\u64cd", "tags": ["\u5c0f\u5b9d", "\u5bfb\u82b1", "\u7ea6", "\u4e86", "\u4e2a", "\u725b\u4ed4\u88e4", "\u767d\u8863", "\u59b9\u5b50", "\u556a\u556a", "\uff0c", "\u53e3\u4ea4", "\u8214", "\u5f04", "\u4e0a\u4f4d", "\u9a91\u4e58", "\u540e\u5165", "\u62bd\u63d2", "\u5927\u529b", "\u731b\u64cd"], "thumbUrl": "https://thumb.tapecontent.net/thumb/aRqpGgPvYOux3Yk/aRx7ymWABduxqQ4.jpg"}, {"name": "\u5c0f\u5b9d\u5bfb\u82b1\u9ed1\u88d9\u5927\u957f\u817f\u6027\u611f\u5fa1\u59d0TP\u556a\u556a\uff0c\u8131\u5149\u5750\u5728\u8eab\u4e0a\u5939JJ\u6478\u903c\u53e3\u4ea4\uff0c\u4e0a\u4f4d\u9a91\u4e58\u540e\u5165\u731b\u64cd\u547b\u541f\u8bf1\u4eba", "size": 118375114, "link": "https://streamtape.com/e/9l06yZyzBJi93G", "created_at": "2022\u5e7403\u670813\u65e5 08:20:34", "downloads": 0, "linkid": "9l06yZyzBJi93G", "convert": "converted", "achorname": "\u4e38\u5b50\u5466", "subscribe": "128.6\u4e07\u4f4d\u8ba2\u9605\u8005", "avatar-img": "https://huyaimg.msstatic.com/avatar/1022/07/ec5fef7c7662720286fbbb12395390_180_135.jpg?1628178596?457957", "folderName": "\u5c0f\u5b9d\u5bfb\u82b1\u9ed1\u88d9\u5927\u957f\u817f\u6027\u611f\u5fa1\u59d0TP\u556a\u556a\uff0c\u8131\u5149\u5750\u5728\u8eab\u4e0a\u5939JJ\u6478\u903c\u53e3\u4ea4\uff0c\u4e0a\u4f4d\u9a91\u4e58\u540e\u5165\u731b\u64cd\u547b\u541f\u8bf1\u4eba", "tags": ["\u5c0f\u5b9d", "\u5bfb\u82b1", "\u9ed1\u88d9", "\u5927\u957f", "\u817f", "\u6027\u611f", "\u5fa1\u59d0", "TP", "\u556a\u556a", "\uff0c", "\u8131\u5149", "\u5750\u5728", "\u8eab\u4e0a", "\u5939", "JJ", "\u6478", "\u903c", "\u53e3\u4ea4", "\uff0c", "\u4e0a\u4f4d", "\u9a91\u4e58", "\u540e\u5165", "\u731b\u64cd", "\u547b\u541f", "\u8bf1\u4eba"], "thumbUrl": "https://thumb.tapecontent.net/thumb/9l06yZyzBJi93G/BXXYo01QLxcyoWJ.jpg"}, {"name": "\u5c0f\u5b9d\u5bfb\u82b1\u9f50\u903c\u77ed\u88e4\u989c\u503c\u4e0d\u9519\u82d7\u6761\u59b9\u5b50\uff0c\u9a91\u5728\u8eab\u4e0a\u8c03\u60c569\u53e3\u4ea4\u4fa7\u5165\u731b\u64cd\uff0c\u547b\u541f\u5a07\u5598\u975e\u5e38\u8bf1\u4eba", "size": 86801074, "link": "https://streamtape.com/e/OP3DlVZbGATegA", "created_at": "2022\u5e7403\u670813\u65e5 08:37:24", "downloads": 0, "linkid": "OP3DlVZbGATegA", "convert": "converted", "achorname": "\u4e38\u5b50\u5466", "subscribe": "128.6\u4e07\u4f4d\u8ba2\u9605\u8005", "avatar-img": "https://huyaimg.msstatic.com/avatar/1022/07/ec5fef7c7662720286fbbb12395390_180_135.jpg?1628178596?457957", "folderName": "\u5c0f\u5b9d\u5bfb\u82b1\u9f50\u903c\u77ed\u88e4\u989c\u503c\u4e0d\u9519\u82d7\u6761\u59b9\u5b50\uff0c\u9a91\u5728\u8eab\u4e0a\u8c03\u60c569\u53e3\u4ea4\u4fa7\u5165\u731b\u64cd\uff0c\u547b\u541f\u5a07\u5598\u975e\u5e38\u8bf1\u4eba", "tags": ["\u5c0f\u5b9d", "\u5bfb\u82b1\u9f50", "\u903c", "\u77ed\u88e4", "\u989c\u503c", "\u4e0d\u9519", "\u82d7\u6761", "\u59b9\u5b50", "\uff0c", "\u9a91", "\u5728", "\u8eab\u4e0a", "\u8c03\u60c5", "69", "\u53e3\u4ea4", "\u4fa7\u5165", "\u731b\u64cd", "\uff0c", "\u547b\u541f", "\u5a07\u5598", "\u975e\u5e38", "\u8bf1\u4eba"], "thumbUrl": "https://thumb.tapecontent.net/thumb/OP3DlVZbGATegA/7YyXpzOg9aIYyy.jpg"}, {"name": "\u674e\u5bfb\u6b22\u63a2\u82b1\u7ea6\u4e86\u4e2a\u989c\u503c\u4e0d\u9519\u767d\u8863\u59b9\u5b50\u556a\u556a\uff0c\u7a7f\u4e0a\u60c5\u8da3\u88c5\u9ed1\u4e1d\u6df1\u5589\u53e3\u4ea4\u540e\u5165\u731b\u64cd", "size": 190943258, "link": "https://streamtape.com/e/BJlJLLk3KaiyOBA", "created_at": "2022\u5e7403\u670814\u65e5 14:15:23", "downloads": 0, "linkid": "BJlJLLk3KaiyOBA", "convert": "converted", "achorname": "\u4e38\u5b50\u5466", "subscribe": "128.6\u4e07\u4f4d\u8ba2\u9605\u8005", "avatar-img": "https://huyaimg.msstatic.com/avatar/1022/07/ec5fef7c7662720286fbbb12395390_180_135.jpg?1628178596?457957", "folderName": "\u674e\u5bfb\u6b22\u63a2\u82b1\u7ea6\u4e86\u4e2a\u989c\u503c\u4e0d\u9519\u767d\u8863\u59b9\u5b50\u556a\u556a\uff0c\u7a7f\u4e0a\u60c5\u8da3\u88c5\u9ed1\u4e1d\u6df1\u5589\u53e3\u4ea4\u540e\u5165\u731b\u64cd", "tags": ["\u674e\u5bfb\u6b22", "\u63a2\u82b1", "\u7ea6", "\u4e86", "\u4e2a", "\u989c\u503c", "\u4e0d\u9519", "\u767d\u8863", "\u59b9\u5b50", "\u556a\u556a", "\uff0c", "\u7a7f", "\u4e0a", "\u60c5\u8da3", "\u88c5\u9ed1\u4e1d", "\u6df1\u5589", "\u53e3\u4ea4", "\u540e\u5165", "\u731b\u64cd"], "thumbUrl": "https://thumb.tapecontent.net/thumb/BJlJLLk3KaiyOBA/y2rxBOOz0QFo6x.jpg"}, {"name": "\u5c0f\u5b9d\u5bfb\u82b1\u7b2c\u4e8c\u573a\u7ea6\u4e86\u4e2a\u6781\u54c1\u989c\u503c\u82d7\u6761\u957f\u817f\u7f8e\u5973\uff0c\u53e3\u4ea4\u8214\u5f04\u4e0a\u4f4d\u9a91\u4e58\u62bd\u63d2\u731b\u64cd\u547b\u541f\u8bf1\u4eba", "size": 153768003, "link": "https://streamtape.com/e/1DqXwQ7oQZIe4qy", "created_at": "2022\u5e7403\u670813\u65e5 05:51:02", "downloads": 0, "linkid": "1DqXwQ7oQZIe4qy", "convert": "converted", "achorname": "\u4e38\u5b50\u5466", "subscribe": "128.6\u4e07\u4f4d\u8ba2\u9605\u8005", "avatar-img": "https://huyaimg.msstatic.com/avatar/1022/07/ec5fef7c7662720286fbbb12395390_180_135.jpg?1628178596?457957", "folderName": "\u5c0f\u5b9d\u5bfb\u82b1\u7b2c\u4e8c\u573a\u7ea6\u4e86\u4e2a\u6781\u54c1\u989c\u503c\u82d7\u6761\u957f\u817f\u7f8e\u5973\uff0c\u53e3\u4ea4\u8214\u5f04\u4e0a\u4f4d\u9a91\u4e58\u62bd\u63d2\u731b\u64cd\u547b\u541f\u8bf1\u4eba", "tags": ["\u5c0f\u5b9d", "\u5bfb\u82b1", "\u7b2c\u4e8c\u573a", "\u7ea6", "\u4e86", "\u4e2a", "\u6781\u54c1", "\u989c\u503c", "\u82d7\u6761", "\u957f\u817f", "\u7f8e\u5973", "\uff0c", "\u53e3\u4ea4", "\u8214", "\u5f04", "\u4e0a\u4f4d", "\u9a91\u4e58", "\u62bd\u63d2", "\u731b\u64cd", "\u547b\u541f", "\u8bf1\u4eba"], "thumbUrl": "https://thumb.tapecontent.net/thumb/1DqXwQ7oQZIe4qy/6wvdvBVBeRC4jG.jpg"}, {"name": "\u5c0f\u5b9d\u5bfb\u82b1\u7b2c\u4e8c\u573a\u6781\u54c1\u989c\u503c\u82d7\u6761\u957f\u817f\u7f8e\u5973\uff0c\u8214\u5f04\u4e0a\u4f4d\u9a91\u4e58\u62bd\u63d2\u731b\u64cd\u547b\u541f", "size": 153085332, "link": "https://streamtape.com/e/jlJARa0BkZF2Zm", "created_at": "2022\u5e7403\u670813\u65e5 05:56:10", "downloads": 0, "linkid": "jlJARa0BkZF2Zm", "convert": "converted", "achorname": "\u4e38\u5b50\u5466", "subscribe": "128.6\u4e07\u4f4d\u8ba2\u9605\u8005", "avatar-img": "https://huyaimg.msstatic.com/avatar/1022/07/ec5fef7c7662720286fbbb12395390_180_135.jpg?1628178596?457957", "folderName": "\u5c0f\u5b9d\u5bfb\u82b1\u7b2c\u4e8c\u573a\u6781\u54c1\u989c\u503c\u82d7\u6761\u957f\u817f\u7f8e\u5973\uff0c\u8214\u5f04\u4e0a\u4f4d\u9a91\u4e58\u62bd\u63d2\u731b\u64cd\u547b\u541f", "tags": ["\u5c0f\u5b9d", "\u5bfb\u82b1", "\u7b2c\u4e8c\u573a", "\u6781\u54c1", "\u989c\u503c", "\u82d7\u6761", "\u957f\u817f", "\u7f8e\u5973", "\uff0c", "\u8214", "\u5f04", "\u4e0a\u4f4d", "\u9a91\u4e58", "\u62bd\u63d2", "\u731b\u64cd", "\u547b\u541f"], "thumbUrl": "https://thumb.tapecontent.net/thumb/jlJARa0BkZF2Zm/dp0MgParlzhkYKq.jpg"}, {"name": "\u5c0f\u5b9d\u5bfb\u82b1\u7b11\u8d77\u6765\u751c\u7f8e\u767d\u8863\u5916\u56f4\u59b9\u5b50\uff0c\u6709\u70b9\u7d27\u5f20\u5750\u5728\u8eab\u4e0a\u820c\u543b\u4e92\u6478\uff0c\u8fd1\u8ddd\u79bb\u62cd\u6444\u6df1\u5589\u53e3\u4ea4\uff0c\u540e\u5165\u4e0a\u4f4d\u9a91\u5750\u731b\u64cd", "size": 152764477, "link": "https://streamtape.com/e/Yw1dg03qMOtv0D3", "created_at": "2022\u5e7403\u670813\u65e5 03:57:34", "downloads": 0, "linkid": "Yw1dg03qMOtv0D3", "convert": "converted", "achorname": "\u4e38\u5b50\u5466", "subscribe": "128.6\u4e07\u4f4d\u8ba2\u9605\u8005", "avatar-img": "https://huyaimg.msstatic.com/avatar/1022/07/ec5fef7c7662720286fbbb12395390_180_135.jpg?1628178596?457957", "folderName": "\u5c0f\u5b9d\u5bfb\u82b1\u7b11\u8d77\u6765\u751c\u7f8e\u767d\u8863\u5916\u56f4\u59b9\u5b50\uff0c\u6709\u70b9\u7d27\u5f20\u5750\u5728\u8eab\u4e0a\u820c\u543b\u4e92\u6478\uff0c\u8fd1\u8ddd\u79bb\u62cd\u6444\u6df1\u5589\u53e3\u4ea4\uff0c\u540e\u5165\u4e0a\u4f4d\u9a91\u5750\u731b\u64cd", "tags": ["\u5c0f\u5b9d", "\u5bfb\u82b1", "\u7b11", "\u8d77\u6765", "\u751c\u7f8e", "\u767d\u8863", "\u5916\u56f4", "\u59b9\u5b50", "\uff0c", "\u6709\u70b9", "\u7d27\u5f20", "\u5750\u5728", "\u8eab\u4e0a", "\u820c\u543b", "\u4e92\u6478", "\uff0c", "\u8fd1\u8ddd\u79bb", "\u62cd\u6444", "\u6df1\u5589", "\u53e3\u4ea4", "\uff0c", "\u540e\u5165", "\u4e0a\u4f4d", "\u9a91\u5750", "\u731b\u64cd"], "thumbUrl": "https://thumb.tapecontent.net/thumb/Yw1dg03qMOtv0D3/qMWpDPdgw8uzeD8.jpg"}, {"name": "\u60c5\u611f\u4e3b\u535a\u674e\u5bfb\u6b22\u7b2c\u4e8c\u573a\u989c\u503c\u4e0d\u9519\u767d\u8863\u59b9\u5b50\u556a\u556a\uff0c\u6d17\u5b8c\u6fa1\u53e3\u4ea4\u8214\u5f04\u9a91\u5750\u81ea\u5df1\u52a8\u7fd8\u5c41\u80a1\u540e\u5165", "size": 179424365, "link": "https://streamtape.com/e/7qlYxyAMwVhA9qQ", "created_at": "2022\u5e7403\u670814\u65e5 13:50:19", "downloads": 0, "linkid": "7qlYxyAMwVhA9qQ", "convert": "converted", "achorname": "\u4e38\u5b50\u5466", "subscribe": "128.6\u4e07\u4f4d\u8ba2\u9605\u8005", "avatar-img": "https://huyaimg.msstatic.com/avatar/1022/07/ec5fef7c7662720286fbbb12395390_180_135.jpg?1628178596?457957", "folderName": "\u60c5\u611f\u4e3b\u535a\u674e\u5bfb\u6b22\u7b2c\u4e8c\u573a\u989c\u503c\u4e0d\u9519\u767d\u8863\u59b9\u5b50\u556a\u556a\uff0c\u6d17\u5b8c\u6fa1\u53e3\u4ea4\u8214\u5f04\u9a91\u5750\u81ea\u5df1\u52a8\u7fd8\u5c41\u80a1\u540e\u5165", "tags": ["\u60c5\u611f", "\u4e3b\u535a", "\u674e\u5bfb\u6b22", "\u7b2c\u4e8c\u573a", "\u989c\u503c", "\u4e0d\u9519", "\u767d\u8863", "\u59b9\u5b50", "\u556a\u556a", "\uff0c", "\u6d17\u5b8c", "\u6fa1", "\u53e3\u4ea4", "\u8214", "\u5f04", "\u9a91\u5750", "\u81ea\u5df1", "\u52a8\u7fd8", "\u5c41\u80a1", "\u540e\u5165"], "thumbUrl": "https://thumb.tapecontent.net/thumb/7qlYxyAMwVhA9qQ/el2ZW08wY8cYVWW.jpg"}, {"name": "\u5c0f\u5b9d\u5bfb\u82b1\u7ea6\u4e86\u4e2a\u8089\u8089\u8eab\u6750\u957f\u76f8\u751c\u7f8e\u9ed1\u8863\u840c\u59b9\u556a\u556a\uff0c\u5750\u5728\u8eab\u4e0a\u820c\u543b\u8c03\u60c5\u53e3\u4ea4\u6478\u903c\u62bd\u63d2\u731b\u64cd", "size": 187215602, "link": "https://streamtape.com/e/6eQ2y64mwpF9rWA", "created_at": "2022\u5e7403\u670813\u65e5 04:39:45", "downloads": 0, "linkid": "6eQ2y64mwpF9rWA", "convert": "converted", "achorname": "\u4e38\u5b50\u5466", "subscribe": "128.6\u4e07\u4f4d\u8ba2\u9605\u8005", "avatar-img": "https://huyaimg.msstatic.com/avatar/1022/07/ec5fef7c7662720286fbbb12395390_180_135.jpg?1628178596?457957", "folderName": "\u5c0f\u5b9d\u5bfb\u82b1\u7ea6\u4e86\u4e2a\u8089\u8089\u8eab\u6750\u957f\u76f8\u751c\u7f8e\u9ed1\u8863\u840c\u59b9\u556a\u556a\uff0c\u5750\u5728\u8eab\u4e0a\u820c\u543b\u8c03\u60c5\u53e3\u4ea4\u6478\u903c\u62bd\u63d2\u731b\u64cd", "tags": ["\u5c0f\u5b9d", "\u5bfb\u82b1", "\u7ea6", "\u4e86", "\u4e2a", "\u8089", "\u8089", "\u8eab\u6750", "\u957f\u76f8", "\u751c\u7f8e", "\u9ed1\u8863", "\u840c\u59b9", "\u556a\u556a", "\uff0c", "\u5750\u5728", "\u8eab\u4e0a", "\u820c\u543b", "\u8c03\u60c5", "\u53e3\u4ea4", "\u6478", "\u903c", "\u62bd\u63d2", "\u731b\u64cd"], "thumbUrl": "https://thumb.tapecontent.net/thumb/6eQ2y64mwpF9rWA/YB41dyL4xOUvWWj.jpg"}, {"name": "\u5c0f\u5b9d\u5bfb\u82b1\u6df1\u591c\u573a\u9ad8\u7d20\u8d28\u5927\u5708\u5916\u56f4\uff0c\u6587\u9759\u59b9\u5b50\u5750\u5728\u8eab\u4e0a\u63c9\u634f\u5976\u5b50\uff0c\u820c\u543b\u8dea\u7740\u53e3\u4ea4\u7279\u5199\uff0c\u9a91\u4e58\u62ac\u817f\u4fa7\u5165\u547b\u541f\u5a07\u5598\u4eab\u53d7", "size": 136459401, "link": "https://streamtape.com/e/D9dee7wo40HkZ6k", "created_at": "2022\u5e7403\u670812\u65e5 18:10:23", "downloads": 0, "linkid": "D9dee7wo40HkZ6k", "convert": "converted", "achorname": "\u4e38\u5b50\u5466", "subscribe": "128.6\u4e07\u4f4d\u8ba2\u9605\u8005", "avatar-img": "https://huyaimg.msstatic.com/avatar/1022/07/ec5fef7c7662720286fbbb12395390_180_135.jpg?1628178596?457957", "folderName": "\u5c0f\u5b9d\u5bfb\u82b1\u6df1\u591c\u573a\u9ad8\u7d20\u8d28\u5927\u5708\u5916\u56f4\uff0c\u6587\u9759\u59b9\u5b50\u5750\u5728\u8eab\u4e0a\u63c9\u634f\u5976\u5b50\uff0c\u820c\u543b\u8dea\u7740\u53e3\u4ea4\u7279\u5199\uff0c\u9a91\u4e58\u62ac\u817f\u4fa7\u5165\u547b\u541f\u5a07\u5598\u4eab\u53d7", "tags": ["\u5c0f\u5b9d", "\u5bfb\u82b1", "\u6df1\u591c", "\u573a", "\u9ad8\u7d20\u8d28", "\u5927", "\u5708", "\u5916\u56f4", "\uff0c", "\u6587\u9759", "\u59b9\u5b50", "\u5750\u5728", "\u8eab\u4e0a", "\u63c9\u634f", "\u5976\u5b50", "\uff0c", "\u820c", "\u543b", "\u8dea", "\u7740", "\u53e3\u4ea4", "\u7279\u5199", "\uff0c", "\u9a91\u4e58", "\u62ac\u817f", "\u4fa7\u5165", "\u547b\u541f", "\u5a07\u5598", "\u4eab\u53d7"], "thumbUrl": "https://thumb.tapecontent.net/thumb/D9dee7wo40HkZ6k/A1OkDz4RZYiX0xW.jpg"}, {"name": "\u4e03\u5929\u6781\u54c1\u63a2\u82b1\u7ea6\u4e86\u4e2a\u989c\u503c\u4e0d\u9519\u9ed1\u8863\u59b9\u5b50\u556a\u556a\uff0c\u7a7f\u4e0a\u9ed1\u4e1d\u63b0\u7a74\u6478\u903c\u4fa7\u5165\u62bd\u63d2\u62b1\u8d77\u6765\u731b\u64cd", "size": 179953035, "link": "https://streamtape.com/e/O2Rbk8dmqKT9L3", "created_at": "2022\u5e7403\u670814\u65e5 04:45:58", "downloads": 0, "linkid": "O2Rbk8dmqKT9L3", "convert": "converted", "achorname": "\u4e38\u5b50\u5466", "subscribe": "128.6\u4e07\u4f4d\u8ba2\u9605\u8005", "avatar-img": "https://huyaimg.msstatic.com/avatar/1022/07/ec5fef7c7662720286fbbb12395390_180_135.jpg?1628178596?457957", "folderName": "\u4e03\u5929\u6781\u54c1\u63a2\u82b1\u7ea6\u4e86\u4e2a\u989c\u503c\u4e0d\u9519\u9ed1\u8863\u59b9\u5b50\u556a\u556a\uff0c\u7a7f\u4e0a\u9ed1\u4e1d\u63b0\u7a74\u6478\u903c\u4fa7\u5165\u62bd\u63d2\u62b1\u8d77\u6765\u731b\u64cd", "tags": ["\u4e03\u5929", "\u6781\u54c1", "\u63a2\u82b1", "\u7ea6", "\u4e86", "\u4e2a", "\u989c\u503c", "\u4e0d\u9519", "\u9ed1\u8863", "\u59b9\u5b50", "\u556a\u556a", "\uff0c", "\u7a7f", "\u4e0a", "\u9ed1\u4e1d", "\u63b0", "\u7a74", "\u6478", "\u903c", "\u4fa7\u5165", "\u62bd\u63d2", "\u62b1", "\u8d77\u6765", "\u731b\u64cd"], "thumbUrl": "https://thumb.tapecontent.net/thumb/O2Rbk8dmqKT9L3/vWMrdq9399f44J7.jpg"}, {"name": "\u5c0f\u5b9d\u5bfb\u82b1\u5927\u6ce2\u6d6a\u767d\u8863\u77ed\u88e4\u5916\u56f4\uff0c\u5750\u5728\u8eab\u4e0a\u820c\u543b\u9694\u7740\u5185\u88e4\u6478\u903c\uff0c\u8fd1\u8ddd\u79bb\u62cd\u6444\u5e8a\u4e0a\u8214\u5c4c\uff0c\u4fa7\u5165\u540e\u5165\u62bd\u63d2\u731b\u64cd", "size": 161194541, "link": "https://streamtape.com/e/Qrw2ZLqjkrc0byQ", "created_at": "2022\u5e7403\u670812\u65e5 18:17:21", "downloads": 0, "linkid": "Qrw2ZLqjkrc0byQ", "convert": "converted", "achorname": "\u4e38\u5b50\u5466", "subscribe": "128.6\u4e07\u4f4d\u8ba2\u9605\u8005", "avatar-img": "https://huyaimg.msstatic.com/avatar/1022/07/ec5fef7c7662720286fbbb12395390_180_135.jpg?1628178596?457957", "folderName": "\u5c0f\u5b9d\u5bfb\u82b1\u5927\u6ce2\u6d6a\u767d\u8863\u77ed\u88e4\u5916\u56f4\uff0c\u5750\u5728\u8eab\u4e0a\u820c\u543b\u9694\u7740\u5185\u88e4\u6478\u903c\uff0c\u8fd1\u8ddd\u79bb\u62cd\u6444\u5e8a\u4e0a\u8214\u5c4c\uff0c\u4fa7\u5165\u540e\u5165\u62bd\u63d2\u731b\u64cd", "tags": ["\u5c0f\u5b9d", "\u5bfb\u82b1", "\u5927\u6ce2\u6d6a", "\u767d\u8863", "\u77ed\u88e4", "\u5916\u56f4", "\uff0c", "\u5750\u5728", "\u8eab\u4e0a", "\u820c", "\u543b", "\u9694", "\u7740", "\u5185\u88e4", "\u6478", "\u903c", "\uff0c", "\u8fd1\u8ddd\u79bb", "\u62cd\u6444", "\u5e8a\u4e0a", "\u8214", "\u5c4c", "\uff0c", "\u4fa7\u5165", "\u540e\u5165", "\u62bd\u63d2", "\u731b\u64cd"], "thumbUrl": "https://thumb.tapecontent.net/thumb/Qrw2ZLqjkrc0byQ/dP1klDl42lIkROV.jpg"}, {"name": "\u5c0f\u5b9d\u5bfb\u82b1\u7ea6\u4e86\u4e2a\u989c\u503c\u4e0d\u9519\u82b1\u81c2\u7eb9\u8eab\u725b\u4ed4\u88e4\u59b9\u5b50\uff0c\u8214\u5f04\u4e92\u6478\u53e3\u4ea4\u4e0a\u4f4d\u9a91\u4e58\u5927\u529b\u62bd\u63d2\u731b\u64cd", "size": 119193944, "link": "https://streamtape.com/e/g23VvoewOxTq70A", "created_at": "2022\u5e7403\u670813\u65e5 09:42:05", "downloads": 0, "linkid": "g23VvoewOxTq70A", "convert": "converted", "achorname": "\u4e38\u5b50\u5466", "subscribe": "128.6\u4e07\u4f4d\u8ba2\u9605\u8005", "avatar-img": "https://huyaimg.msstatic.com/avatar/1022/07/ec5fef7c7662720286fbbb12395390_180_135.jpg?1628178596?457957", "folderName": "\u5c0f\u5b9d\u5bfb\u82b1\u7ea6\u4e86\u4e2a\u989c\u503c\u4e0d\u9519\u82b1\u81c2\u7eb9\u8eab\u725b\u4ed4\u88e4\u59b9\u5b50\uff0c\u8214\u5f04\u4e92\u6478\u53e3\u4ea4\u4e0a\u4f4d\u9a91\u4e58\u5927\u529b\u62bd\u63d2\u731b\u64cd", "tags": ["\u5c0f\u5b9d", "\u5bfb\u82b1", "\u7ea6", "\u4e86", "\u4e2a", "\u989c\u503c", "\u4e0d\u9519", "\u82b1\u81c2", "\u7eb9\u8eab", "\u725b\u4ed4\u88e4", "\u59b9\u5b50", "\uff0c", "\u8214", "\u5f04", "\u4e92\u6478\u53e3", "\u4ea4\u4e0a", "\u4f4d", "\u9a91\u4e58", "\u5927\u529b", "\u62bd\u63d2", "\u731b\u64cd"], "thumbUrl": "https://thumb.tapecontent.net/thumb/g23VvoewOxTq70A/Og2AW1BKm6uZA39.jpg"}, {"name": "\u5c0f\u5b9d\u5bfb\u82b1\u7b2c\u4e8c\u573a\u82d7\u6761\u59b9\u5b50\u6c99\u53d1\u820c\u543b\u8c03\u60c5\uff0c\u5750\u5728\u8eab\u4e0a\u5f20\u5f00\u53cc\u817f\u6478\u903c\uff0c\u4e0a\u4f4d\u9a91\u4e58\u4fa7\u5165\u731b\u64cd\u547b\u541f\u5a07\u5598", "size": 171322575, "link": "https://streamtape.com/e/wr47jemWRghJOyz", "created_at": "2022\u5e7403\u670813\u65e5 08:10:50", "downloads": 0, "linkid": "wr47jemWRghJOyz", "convert": "converted", "achorname": "\u4e38\u5b50\u5466", "subscribe": "128.6\u4e07\u4f4d\u8ba2\u9605\u8005", "avatar-img": "https://huyaimg.msstatic.com/avatar/1022/07/ec5fef7c7662720286fbbb12395390_180_135.jpg?1628178596?457957", "folderName": "\u5c0f\u5b9d\u5bfb\u82b1\u7b2c\u4e8c\u573a\u82d7\u6761\u59b9\u5b50\u6c99\u53d1\u820c\u543b\u8c03\u60c5\uff0c\u5750\u5728\u8eab\u4e0a\u5f20\u5f00\u53cc\u817f\u6478\u903c\uff0c\u4e0a\u4f4d\u9a91\u4e58\u4fa7\u5165\u731b\u64cd\u547b\u541f\u5a07\u5598", "tags": ["\u5c0f\u5b9d", "\u5bfb\u82b1", "\u7b2c\u4e8c\u573a", "\u82d7\u6761", "\u59b9\u5b50", "\u6c99\u53d1", "\u820c\u543b", "\u8c03\u60c5", "\uff0c", "\u5750\u5728", "\u8eab\u4e0a", "\u5f20\u5f00", "\u53cc\u817f", "\u6478", "\u903c", "\uff0c", "\u4e0a\u4f4d", "\u9a91\u4e58", "\u4fa7\u5165", "\u731b\u64cd", "\u547b\u541f", "\u5a07\u5598"], "thumbUrl": "https://thumb.tapecontent.net/thumb/wr47jemWRghJOyz/D0pLyj4GXyUkMk6.jpg"}, {"name": "\u5c0f\u5b9d\u5bfb\u82b1\u5927\u795e\u5e26\u4f60\u627e\u5916\u56f4\uff0c\u6591\u70b9\u88d9\u7b11\u8d77\u6765\u751c\u7f8e100\u65a4\u59b9\u5b50\uff0c\u6df1\u5589\u53e3\u4ea4\u559c\u6b22\u5728\u4e0a\u9762\uff0c\u9a91\u4e58\u62bd\u63d2\u6478\u7740\u5976\u5b50\u540e\u5165\u731b\u64cd", "size": 145845385, "link": "https://streamtape.com/e/Lq2zDolOp6tRGO1", "created_at": "2022\u5e7403\u670812\u65e5 18:07:48", "downloads": 0, "linkid": "Lq2zDolOp6tRGO1", "convert": "converted", "achorname": "\u4e38\u5b50\u5466", "subscribe": "128.6\u4e07\u4f4d\u8ba2\u9605\u8005", "avatar-img": "https://huyaimg.msstatic.com/avatar/1022/07/ec5fef7c7662720286fbbb12395390_180_135.jpg?1628178596?457957", "folderName": "\u5c0f\u5b9d\u5bfb\u82b1\u5927\u795e\u5e26\u4f60\u627e\u5916\u56f4\uff0c\u6591\u70b9\u88d9\u7b11\u8d77\u6765\u751c\u7f8e100\u65a4\u59b9\u5b50\uff0c\u6df1\u5589\u53e3\u4ea4\u559c\u6b22\u5728\u4e0a\u9762\uff0c\u9a91\u4e58\u62bd\u63d2\u6478\u7740\u5976\u5b50\u540e\u5165\u731b\u64cd", "tags": ["\u5c0f\u5b9d", "\u5bfb\u82b1", "\u5927\u795e", "\u5e26", "\u4f60", "\u627e", "\u5916\u56f4", "\uff0c", "\u6591\u70b9", "\u88d9\u7b11", "\u8d77\u6765", "\u751c\u7f8e", "100", "\u65a4", "\u59b9\u5b50", "\uff0c", "\u6df1\u5589", "\u53e3\u4ea4", "\u559c\u6b22", "\u5728", "\u4e0a\u9762", "\uff0c", "\u9a91\u4e58", "\u62bd\u63d2", "\u6478", "\u7740", "\u5976\u5b50", "\u540e\u5165", "\u731b\u64cd"], "thumbUrl": "https://thumb.tapecontent.net/thumb/Lq2zDolOp6tRGO1/MZzaL0lPAXsmOLJ.jpg"}, {"name": "\u5c0f\u5b9d\u5bfb\u82b1\u5927\u795e\u9ad8\u7aef\u5927\u5708\u5916\u56f4\u59b9\u5b50\uff0c\u82b1\u81c2\u7eb9\u8eab\u767d\u88d9\u5c0f\u59d0\u59d0\uff0c\u5750\u5728\u8eab\u4e0a\u6478\u5976\u820c\u543b\u8c03\u60c5\uff0c\u6276\u7740\u53cc\u817f\u62bd\u63d2\u547b\u541f\u5a07\u5598", "size": 82577876, "link": "https://streamtape.com/e/xbvreKkxApFkPZ8", "created_at": "2022\u5e7403\u670813\u65e5 09:49:49", "downloads": 0, "linkid": "xbvreKkxApFkPZ8", "convert": "converted", "achorname": "\u4e38\u5b50\u5466", "subscribe": "128.6\u4e07\u4f4d\u8ba2\u9605\u8005", "avatar-img": "https://huyaimg.msstatic.com/avatar/1022/07/ec5fef7c7662720286fbbb12395390_180_135.jpg?1628178596?457957", "folderName": "\u5c0f\u5b9d\u5bfb\u82b1\u5927\u795e\u9ad8\u7aef\u5927\u5708\u5916\u56f4\u59b9\u5b50\uff0c\u82b1\u81c2\u7eb9\u8eab\u767d\u88d9\u5c0f\u59d0\u59d0\uff0c\u5750\u5728\u8eab\u4e0a\u6478\u5976\u820c\u543b\u8c03\u60c5\uff0c\u6276\u7740\u53cc\u817f\u62bd\u63d2\u547b\u541f\u5a07\u5598", "tags": ["\u5c0f\u5b9d", "\u5bfb\u82b1", "\u5927\u795e", "\u9ad8\u7aef", "\u5927", "\u5708", "\u5916\u56f4", "\u59b9\u5b50", "\uff0c", "\u82b1\u81c2", "\u7eb9\u8eab", "\u767d\u88d9", "\u5c0f\u59d0\u59d0", "\uff0c", "\u5750\u5728", "\u8eab\u4e0a", "\u6478\u5976", "\u820c", "\u543b", "\u8c03\u60c5", "\uff0c", "\u6276", "\u7740", "\u53cc\u817f", "\u62bd\u63d2", "\u547b\u541f", "\u5a07\u5598"], "thumbUrl": "https://thumb.tapecontent.net/thumb/xbvreKkxApFkPZ8/M7Bx0APjD1hwDz.jpg"}, {"name": "\u5c0f\u5b9d\u5bfb\u82b1\u6781\u54c1\u9ad8\u8d28\u91cf\u725b\u4ed4\u88e4\u5916\u56f4\u59b9\u5b50\uff0c\u5750\u5728\u8eab\u4e0a\u8c03\u60c5\u4e00\u756a\u820c\u543b\u6478\u5976\uff0c\u4e0a\u4f4d\u81ea\u5df1\u52a8\u5927\u529b\u731b\u64cd", "size": 120369741, "link": "https://streamtape.com/e/OaXy21MrOduZOO2", "created_at": "2022\u5e7403\u670813\u65e5 08:15:27", "downloads": 0, "linkid": "OaXy21MrOduZOO2", "convert": "converted", "achorname": "\u4e38\u5b50\u5466", "subscribe": "128.6\u4e07\u4f4d\u8ba2\u9605\u8005", "avatar-img": "https://huyaimg.msstatic.com/avatar/1022/07/ec5fef7c7662720286fbbb12395390_180_135.jpg?1628178596?457957", "folderName": "\u5c0f\u5b9d\u5bfb\u82b1\u6781\u54c1\u9ad8\u8d28\u91cf\u725b\u4ed4\u88e4\u5916\u56f4\u59b9\u5b50\uff0c\u5750\u5728\u8eab\u4e0a\u8c03\u60c5\u4e00\u756a\u820c\u543b\u6478\u5976\uff0c\u4e0a\u4f4d\u81ea\u5df1\u52a8\u5927\u529b\u731b\u64cd", "tags": ["\u5c0f\u5b9d", "\u5bfb\u82b1", "\u6781\u54c1", "\u9ad8\u8d28\u91cf", "\u725b\u4ed4\u88e4", "\u5916\u56f4", "\u59b9\u5b50", "\uff0c", "\u5750\u5728", "\u8eab\u4e0a", "\u8c03\u60c5", "\u4e00\u756a", "\u820c\u543b", "\u6478\u5976", "\uff0c", "\u4e0a\u4f4d", "\u81ea\u5df1", "\u52a8", "\u5927\u529b", "\u731b\u64cd"], "thumbUrl": "https://thumb.tapecontent.net/thumb/OaXy21MrOduZOO2/3kl7l26Joqhdqjr.jpg"}, {"name": "\u5c0f\u5b9d\u5bfb\u82b1\u9ebb\u82b1\u8fab\u9f50\u903c\u5c0f\u77ed\u88d9\u5916\u56f4\u7f8e\u5973\uff0c\u8131\u6389\u5185\u88e4\u9694\u7740\u8863\u670d\u6478\u5976\u5b50\uff0c\u8e72\u7740\u53e3\u4ea4\u4fa7\u5165\u62bd\u63d2\uff0c\u9a91\u4e58\u540e\u5165\u5927\u529b\u731b\u64cd", "size": 110688111, "link": "https://streamtape.com/e/PjX01L1d1ghbKz", "created_at": "2022\u5e7403\u670813\u65e5 09:48:41", "downloads": 0, "linkid": "PjX01L1d1ghbKz", "convert": "converted", "achorname": "\u4e38\u5b50\u5466", "subscribe": "128.6\u4e07\u4f4d\u8ba2\u9605\u8005", "avatar-img": "https://huyaimg.msstatic.com/avatar/1022/07/ec5fef7c7662720286fbbb12395390_180_135.jpg?1628178596?457957", "folderName": "\u5c0f\u5b9d\u5bfb\u82b1\u9ebb\u82b1\u8fab\u9f50\u903c\u5c0f\u77ed\u88d9\u5916\u56f4\u7f8e\u5973\uff0c\u8131\u6389\u5185\u88e4\u9694\u7740\u8863\u670d\u6478\u5976\u5b50\uff0c\u8e72\u7740\u53e3\u4ea4\u4fa7\u5165\u62bd\u63d2\uff0c\u9a91\u4e58\u540e\u5165\u5927\u529b\u731b\u64cd", "tags": ["\u5c0f\u5b9d", "\u5bfb\u82b1", "\u9ebb\u82b1", "\u8fab\u9f50", "\u903c", "\u5c0f", "\u77ed\u88d9", "\u5916\u56f4", "\u7f8e\u5973", "\uff0c", "\u8131\u6389", "\u5185\u88e4", "\u9694", "\u7740", "\u8863\u670d", "\u6478", "\u5976\u5b50", "\uff0c", "\u8e72", "\u7740", "\u53e3\u4ea4", "\u4fa7\u5165", "\u62bd\u63d2", "\uff0c", "\u9a91\u4e58", "\u540e\u5165", "\u5927\u529b", "\u731b\u64cd"], "thumbUrl": "https://thumb.tapecontent.net/thumb/PjX01L1d1ghbKz/ap2r2qvAzRHxxMD.jpg"}, {"name": "\u5c0f\u5b9d\u5bfb\u82b1\u7ea6\u4e86\u4e2a\u957f\u76f8\u751c\u7f8e\u767d\u8863\u840c\u59b9\u5b50\uff0c\u53e3\u4ea4\u8214\u5f04\u6478\u903c\u9a91\u4e58\u540e\u5165\u731b\u64cd\u4e0d\u547b\u541f", "size": 100358533, "link": "https://streamtape.com/e/BkewqYz0R7FyAp6", "created_at": "2022\u5e7403\u670813\u65e5 08:16:11", "downloads": 0, "linkid": "BkewqYz0R7FyAp6", "convert": "converted", "achorname": "\u4e38\u5b50\u5466", "subscribe": "128.6\u4e07\u4f4d\u8ba2\u9605\u8005", "avatar-img": "https://huyaimg.msstatic.com/avatar/1022/07/ec5fef7c7662720286fbbb12395390_180_135.jpg?1628178596?457957", "folderName": "\u5c0f\u5b9d\u5bfb\u82b1\u7ea6\u4e86\u4e2a\u957f\u76f8\u751c\u7f8e\u767d\u8863\u840c\u59b9\u5b50\uff0c\u53e3\u4ea4\u8214\u5f04\u6478\u903c\u9a91\u4e58\u540e\u5165\u731b\u64cd\u4e0d\u547b\u541f", "tags": ["\u5c0f\u5b9d", "\u5bfb\u82b1", "\u7ea6", "\u4e86", "\u4e2a", "\u957f\u76f8", "\u751c\u7f8e", "\u767d\u8863", "\u840c", "\u59b9\u5b50", "\uff0c", "\u53e3\u4ea4", "\u8214", "\u5f04", "\u6478", "\u903c", "\u9a91\u4e58", "\u540e\u5165", "\u731b\u64cd", "\u4e0d", "\u547b\u541f"], "thumbUrl": "https://thumb.tapecontent.net/thumb/BkewqYz0R7FyAp6/m6vZWrl7GrFXxe.jpg"}, {"name": "\u5c0f\u5b9d\u5bfb\u82b1\u5927\u795e\u5e26\u4f60\u627e\u5916\u56f4\u59b9\u5b50\uff0c\u957f\u76f8\u751c\u7f8e\u9ed1\u9774JK\u88c5\u840c\u59b9\u5b50\uff0c\u5750\u5728\u8eab\u4e0a\u8c03\u8c03\u60c5\uff0c\u8e72\u7740\u7fd8\u8d77\u5c41\u80a1\u540e\u5165\u731b\u64cd", "size": 178092518, "link": "https://streamtape.com/e/XP0GW3wY7DhDRo3", "created_at": "2022\u5e7403\u670813\u65e5 04:00:08", "downloads": 0, "linkid": "XP0GW3wY7DhDRo3", "convert": "converted", "achorname": "\u4e38\u5b50\u5466", "subscribe": "128.6\u4e07\u4f4d\u8ba2\u9605\u8005", "avatar-img": "https://huyaimg.msstatic.com/avatar/1022/07/ec5fef7c7662720286fbbb12395390_180_135.jpg?1628178596?457957", "folderName": "\u5c0f\u5b9d\u5bfb\u82b1\u5927\u795e\u5e26\u4f60\u627e\u5916\u56f4\u59b9\u5b50\uff0c\u957f\u76f8\u751c\u7f8e\u9ed1\u9774JK\u88c5\u840c\u59b9\u5b50\uff0c\u5750\u5728\u8eab\u4e0a\u8c03\u8c03\u60c5\uff0c\u8e72\u7740\u7fd8\u8d77\u5c41\u80a1\u540e\u5165\u731b\u64cd", "tags": ["\u5c0f\u5b9d", "\u5bfb\u82b1", "\u5927\u795e", "\u5e26", "\u4f60", "\u627e", "\u5916\u56f4", "\u59b9\u5b50", "\uff0c", "\u957f\u76f8", "\u751c\u7f8e", "\u9ed1\u9774", "JK", "\u88c5\u840c", "\u59b9\u5b50", "\uff0c", "\u5750\u5728", "\u8eab\u4e0a", "\u8c03", "\u8c03\u60c5", "\uff0c", "\u8e72", "\u7740", "\u7fd8\u8d77", "\u5c41\u80a1", "\u540e\u5165", "\u731b\u64cd"], "thumbUrl": "https://thumb.tapecontent.net/thumb/XP0GW3wY7DhDRo3/akJOkGx29dF0yr.jpg"}, {"name": "\u5c0f\u5b9d\u5bfb\u82b1\u9ed1\u8272\u5916\u5957\u840c\u59b9\uff0c\u7a7f\u7740\u8863\u670d\u4e00\u822c\u822c\u8131\u6389\u8eab\u6750\u5c45\u7136\u4e0d\u9519\uff0c\u5e8a\u4e0a\u8dea\u7740\u53e3\u4ea4\u5750\u5728\u8eab\u4e0a\u8815\u52a8\u5c0f\u8170", "size": 190339025, "link": "https://streamtape.com/e/ldRbk2yyA6c7gDY", "created_at": "2022\u5e7403\u670813\u65e5 09:12:15", "downloads": 0, "linkid": "ldRbk2yyA6c7gDY", "convert": "converted", "achorname": "\u4e38\u5b50\u5466", "subscribe": "128.6\u4e07\u4f4d\u8ba2\u9605\u8005", "avatar-img": "https://huyaimg.msstatic.com/avatar/1022/07/ec5fef7c7662720286fbbb12395390_180_135.jpg?1628178596?457957", "folderName": "\u5c0f\u5b9d\u5bfb\u82b1\u9ed1\u8272\u5916\u5957\u840c\u59b9\uff0c\u7a7f\u7740\u8863\u670d\u4e00\u822c\u822c\u8131\u6389\u8eab\u6750\u5c45\u7136\u4e0d\u9519\uff0c\u5e8a\u4e0a\u8dea\u7740\u53e3\u4ea4\u5750\u5728\u8eab\u4e0a\u8815\u52a8\u5c0f\u8170", "tags": ["\u5c0f\u5b9d", "\u5bfb\u82b1", "\u9ed1\u8272", "\u5916\u5957", "\u840c\u59b9", "\uff0c", "\u7a7f\u7740", "\u8863\u670d", "\u4e00\u822c\u822c", "\u8131\u6389", "\u8eab\u6750", "\u5c45\u7136", "\u4e0d\u9519", "\uff0c", "\u5e8a\u4e0a", "\u8dea", "\u7740", "\u53e3\u4ea4", "\u5750\u5728", "\u8eab\u4e0a", "\u8815\u52a8", "\u5c0f\u8170"], "thumbUrl": "https://thumb.tapecontent.net/thumb/ldRbk2yyA6c7gDY/DZvR7KQ8j3fkM4Y.jpg"}, {"name": "\u4e03\u5929\u9ad8\u7aef\u5916\u56f4\u4e4b\u5927\u5976\u5b50\u8f66\u6a21", "size": 370936676, "link": "https://streamtape.com/e/R72Y3qo0QRsd4vl", "created_at": "2022\u5e7403\u670814\u65e5 08:45:40", "downloads": 0, "linkid": "R72Y3qo0QRsd4vl", "convert": "converted", "achorname": "\u4e38\u5b50\u5466", "subscribe": "128.6\u4e07\u4f4d\u8ba2\u9605\u8005", "avatar-img": "https://huyaimg.msstatic.com/avatar/1022/07/ec5fef7c7662720286fbbb12395390_180_135.jpg?1628178596?457957", "folderName": "\u4e03\u5929\u9ad8\u7aef\u5916\u56f4\u4e4b\u5927\u5976\u5b50\u8f66\u6a21", "tags": ["\u4e03\u5929", "\u9ad8\u7aef", "\u5916\u56f4", "\u4e4b\u5927", "\u5976\u5b50", "\u8f66\u6a21"], "thumbUrl": "https://thumb.tapecontent.net/thumb/R72Y3qo0QRsd4vl/rl1XB13481ibV99.jpg"}, {"name": "\u5c0f\u5b9d\u5bfb\u82b1\u989c\u503c\u4e0d\u9519\u7f51\u7ea2\u8138\u59b9\u5b50\uff0c\u53e3\u4ea4\u4e0a\u4f4d\u9a91\u5750\u81ea\u5df1\u52a8\u540e\u4eba\u731b\u64cd\uff0c\u547b\u541f\u5a07\u5598\u975e\u5e38\u8bf1\u4eba", "size": 80017035, "link": "https://streamtape.com/e/JvXmwqdw3vFjkrJ", "created_at": "2022\u5e7403\u670813\u65e5 08:19:14", "downloads": 0, "linkid": "JvXmwqdw3vFjkrJ", "convert": "converted", "achorname": "\u4e38\u5b50\u5466", "subscribe": "128.6\u4e07\u4f4d\u8ba2\u9605\u8005", "avatar-img": "https://huyaimg.msstatic.com/avatar/1022/07/ec5fef7c7662720286fbbb12395390_180_135.jpg?1628178596?457957", "folderName": "\u5c0f\u5b9d\u5bfb\u82b1\u989c\u503c\u4e0d\u9519\u7f51\u7ea2\u8138\u59b9\u5b50\uff0c\u53e3\u4ea4\u4e0a\u4f4d\u9a91\u5750\u81ea\u5df1\u52a8\u540e\u4eba\u731b\u64cd\uff0c\u547b\u541f\u5a07\u5598\u975e\u5e38\u8bf1\u4eba", "tags": ["\u5c0f\u5b9d", "\u5bfb\u82b1", "\u989c\u503c", "\u4e0d\u9519", "\u7f51", "\u7ea2\u8138", "\u59b9\u5b50", "\uff0c", "\u53e3", "\u4ea4\u4e0a", "\u4f4d", "\u9a91\u5750", "\u81ea\u5df1", "\u52a8", "\u540e\u4eba", "\u731b\u64cd", "\uff0c", "\u547b\u541f", "\u5a07\u5598", "\u975e\u5e38", "\u8bf1\u4eba"], "thumbUrl": "https://thumb.tapecontent.net/thumb/JvXmwqdw3vFjkrJ/lDrBQOVpwps7Qj6.jpg"}, {"name": "\u5c0f\u5b9d\u5bfb\u82b1\u7b2c\u4e8c\u573a\u6781\u54c1\u9ad8\u989c\u503c\u751c\u7f8e\u59b9\u5b50\uff0c\u5750\u8eab\u4e0a\u6478\u5c41\u80a1\u820c\u543b\u4e92\u8214\u63d2\u5634\u4e0a\u4f4d\u9a91\u4e58\u731b\u64cd", "size": 245636359, "link": "https://streamtape.com/e/w73VD66kGeCPY9", "created_at": "2022\u5e7403\u670813\u65e5 07:59:48", "downloads": 0, "linkid": "w73VD66kGeCPY9", "convert": "converted", "achorname": "\u4e38\u5b50\u5466", "subscribe": "128.6\u4e07\u4f4d\u8ba2\u9605\u8005", "avatar-img": "https://huyaimg.msstatic.com/avatar/1022/07/ec5fef7c7662720286fbbb12395390_180_135.jpg?1628178596?457957", "folderName": "\u5c0f\u5b9d\u5bfb\u82b1\u7b2c\u4e8c\u573a\u6781\u54c1\u9ad8\u989c\u503c\u751c\u7f8e\u59b9\u5b50\uff0c\u5750\u8eab\u4e0a\u6478\u5c41\u80a1\u820c\u543b\u4e92\u8214\u63d2\u5634\u4e0a\u4f4d\u9a91\u4e58\u731b\u64cd", "tags": ["\u5c0f\u5b9d", "\u5bfb\u82b1", "\u7b2c\u4e8c\u573a", "\u6781\u54c1", "\u9ad8\u989c\u503c", "\u751c\u7f8e", "\u59b9\u5b50", "\uff0c", "\u5750", "\u8eab\u4e0a", "\u6478", "\u5c41\u80a1", "\u820c", "\u543b", "\u4e92", "\u8214", "\u63d2\u5634", "\u4e0a\u4f4d", "\u9a91\u4e58", "\u731b\u64cd"], "thumbUrl": "https://thumb.tapecontent.net/thumb/w73VD66kGeCPY9/RerqABkrYzidbpR.jpg"}, {"name": "\u5c0f\u5b9d\u5bfb\u82b1\u7ea6\u4e86\u4e2a\u6027\u611f\u767d\u8863\u840c\u59b9\u5b50\uff0c\u6c99\u53d1\u820c\u543b\u8c03\u60c5\u53e3\u4ea4\u6478\u903c\uff0c\u518d\u5230\u5e8a\u4e0a\u9a91\u4e58\u540e\u5165\u731b\u64cd", "size": 196677389, "link": "https://streamtape.com/e/rb3xkeAZ43ibPzK", "created_at": "2022\u5e7403\u670813\u65e5 08:06:41", "downloads": 0, "linkid": "rb3xkeAZ43ibPzK", "convert": "converted", "achorname": "\u4e38\u5b50\u5466", "subscribe": "128.6\u4e07\u4f4d\u8ba2\u9605\u8005", "avatar-img": "https://huyaimg.msstatic.com/avatar/1022/07/ec5fef7c7662720286fbbb12395390_180_135.jpg?1628178596?457957", "folderName": "\u5c0f\u5b9d\u5bfb\u82b1\u7ea6\u4e86\u4e2a\u6027\u611f\u767d\u8863\u840c\u59b9\u5b50\uff0c\u6c99\u53d1\u820c\u543b\u8c03\u60c5\u53e3\u4ea4\u6478\u903c\uff0c\u518d\u5230\u5e8a\u4e0a\u9a91\u4e58\u540e\u5165\u731b\u64cd", "tags": ["\u5c0f\u5b9d", "\u5bfb\u82b1", "\u7ea6", "\u4e86", "\u4e2a", "\u6027\u611f", "\u767d\u8863", "\u840c", "\u59b9\u5b50", "\uff0c", "\u6c99\u53d1", "\u820c\u543b", "\u8c03\u60c5", "\u53e3\u4ea4", "\u6478", "\u903c", "\uff0c", "\u518d", "\u5230", "\u5e8a\u4e0a", "\u9a91\u4e58", "\u540e\u5165", "\u731b\u64cd"], "thumbUrl": "https://thumb.tapecontent.net/thumb/rb3xkeAZ43ibPzK/mOxqOJR9W7FbP4z.jpg"}, {"name": "\u63a2\u82b1\u90ce\u674e\u5bfb\u6b2212-20\u5976\u5b50\u5f88\u633a\u7684\u5916\u56f4", "size": 140421848, "link": "https://streamtape.com/e/pDW1l68mvRUrkgm", "created_at": "2022\u5e7403\u670814\u65e5 16:11:13", "downloads": 0, "linkid": "pDW1l68mvRUrkgm", "convert": "converted", "achorname": "\u4e38\u5b50\u5466", "subscribe": "128.6\u4e07\u4f4d\u8ba2\u9605\u8005", "avatar-img": "https://huyaimg.msstatic.com/avatar/1022/07/ec5fef7c7662720286fbbb12395390_180_135.jpg?1628178596?457957", "folderName": "\u63a2\u82b1\u90ce\u674e\u5bfb\u6b2212-20\u5976\u5b50\u5f88\u633a\u7684\u5916\u56f4", "tags": ["\u63a2\u82b1\u90ce", "\u674e\u5bfb\u6b22", "12", "-", "20", "\u5976\u5b50", "\u5f88", "\u633a", "\u7684", "\u5916\u56f4"], "thumbUrl": "https://thumb.tapecontent.net/thumb/pDW1l68mvRUrkgm/kPJJZMrbdBUOJwy.jpg"}, {"name": "\u5c0f\u5b9d\u5bfb\u82b1\u7ea6\u4e86\u4e2a\u767d\u8863\u751c\u7f8e\u59b9\u5b50\uff0c\u53e3\u4ea4\u8214\u5f04\u4e0a\u4f4d\u9a91\u5750\u8fd1\u8ddd\u79bb\u7279\u5199\uff0c\u5927\u529b\u731b\u64cd\u547b\u541f\u5a07\u5598", "size": 222214454, "link": "https://streamtape.com/e/WovjDM4XMJipBJ", "created_at": "2022\u5e7403\u670813\u65e5 08:07:54", "downloads": 0, "linkid": "WovjDM4XMJipBJ", "convert": "converted", "achorname": "\u4e38\u5b50\u5466", "subscribe": "128.6\u4e07\u4f4d\u8ba2\u9605\u8005", "avatar-img": "https://huyaimg.msstatic.com/avatar/1022/07/ec5fef7c7662720286fbbb12395390_180_135.jpg?1628178596?457957", "folderName": "\u5c0f\u5b9d\u5bfb\u82b1\u7ea6\u4e86\u4e2a\u767d\u8863\u751c\u7f8e\u59b9\u5b50\uff0c\u53e3\u4ea4\u8214\u5f04\u4e0a\u4f4d\u9a91\u5750\u8fd1\u8ddd\u79bb\u7279\u5199\uff0c\u5927\u529b\u731b\u64cd\u547b\u541f\u5a07\u5598", "tags": ["\u5c0f\u5b9d", "\u5bfb\u82b1", "\u7ea6", "\u4e86", "\u4e2a", "\u767d\u8863", "\u751c\u7f8e", "\u59b9\u5b50", "\uff0c", "\u53e3\u4ea4", "\u8214", "\u5f04", "\u4e0a\u4f4d", "\u9a91\u5750", "\u8fd1\u8ddd\u79bb", "\u7279\u5199", "\uff0c", "\u5927\u529b", "\u731b\u64cd", "\u547b\u541f", "\u5a07\u5598"], "thumbUrl": "https://thumb.tapecontent.net/thumb/WovjDM4XMJipBJ/oZyRWwBdJlSJqoz.jpg"}, {"name": "\u5c0f\u5b9d\u5bfb\u82b1\u7ea6\u4e86\u4e2a\u989c\u503c\u4e0d\u9519\u5916\u56f4\u59b9\u5b50TP\u556a\u556a\uff0c\u6c99\u53d1\u4e0a\u64cd\u53e3\u4ea4\u9a91\u4e58\u731b\u64cd\uff0c\u6458\u6389\u5957\u5b50\u88ab\u59b9\u5b50\u53d1\u73b0\u4e0d\u8ba9\u505a", "size": 102824645, "link": "https://streamtape.com/e/KARZYykD61T06dx", "created_at": "2022\u5e7403\u670813\u65e5 08:44:26", "downloads": 0, "linkid": "KARZYykD61T06dx", "convert": "converted", "achorname": "\u4e38\u5b50\u5466", "subscribe": "128.6\u4e07\u4f4d\u8ba2\u9605\u8005", "avatar-img": "https://huyaimg.msstatic.com/avatar/1022/07/ec5fef7c7662720286fbbb12395390_180_135.jpg?1628178596?457957", "folderName": "\u5c0f\u5b9d\u5bfb\u82b1\u7ea6\u4e86\u4e2a\u989c\u503c\u4e0d\u9519\u5916\u56f4\u59b9\u5b50TP\u556a\u556a\uff0c\u6c99\u53d1\u4e0a\u64cd\u53e3\u4ea4\u9a91\u4e58\u731b\u64cd\uff0c\u6458\u6389\u5957\u5b50\u88ab\u59b9\u5b50\u53d1\u73b0\u4e0d\u8ba9\u505a", "tags": ["\u5c0f\u5b9d", "\u5bfb\u82b1", "\u7ea6", "\u4e86", "\u4e2a", "\u989c\u503c", "\u4e0d\u9519", "\u5916\u56f4", "\u59b9\u5b50", "TP", "\u556a\u556a", "\uff0c", "\u6c99\u53d1", "\u4e0a\u64cd", "\u53e3\u4ea4", "\u9a91\u4e58", "\u731b\u64cd", "\uff0c", "\u6458\u6389", "\u5957\u5b50", "\u88ab", "\u59b9\u5b50", "\u53d1\u73b0", "\u4e0d\u8ba9", "\u505a"], "thumbUrl": "https://thumb.tapecontent.net/thumb/KARZYykD61T06dx/D907OyadVMTk9lj.jpg"}, {"name": "\u5c0f\u5b9d\u5bfb\u82b1\u7b2c\u4e8c\u573a\u7ea6\u4e86\u4e2a\u6781\u54c1\u989c\u503c\u751c\u7f8e\u59b9\u5b50\u556a\u556a\uff0c\u820c\u543b\u8c03\u60c5\u53e3\u4ea4\u8214\u5976\u9a91\u4e58\u731b\u64cd\u547b\u541f\u5a07\u5598\u8bf1\u4eba", "size": 226516327, "link": "https://streamtape.com/e/8O636L0dvAtooPW", "created_at": "2022\u5e7403\u670813\u65e5 05:53:02", "downloads": 0, "linkid": "8O636L0dvAtooPW", "convert": "converted", "achorname": "\u4e38\u5b50\u5466", "subscribe": "128.6\u4e07\u4f4d\u8ba2\u9605\u8005", "avatar-img": "https://huyaimg.msstatic.com/avatar/1022/07/ec5fef7c7662720286fbbb12395390_180_135.jpg?1628178596?457957", "folderName": "\u5c0f\u5b9d\u5bfb\u82b1\u7b2c\u4e8c\u573a\u7ea6\u4e86\u4e2a\u6781\u54c1\u989c\u503c\u751c\u7f8e\u59b9\u5b50\u556a\u556a\uff0c\u820c\u543b\u8c03\u60c5\u53e3\u4ea4\u8214\u5976\u9a91\u4e58\u731b\u64cd\u547b\u541f\u5a07\u5598\u8bf1\u4eba", "tags": ["\u5c0f\u5b9d", "\u5bfb\u82b1", "\u7b2c\u4e8c\u573a", "\u7ea6", "\u4e86", "\u4e2a", "\u6781\u54c1", "\u989c\u503c", "\u751c\u7f8e", "\u59b9\u5b50", "\u556a\u556a", "\uff0c", "\u820c\u543b", "\u8c03\u60c5", "\u53e3\u4ea4", "\u8214", "\u5976", "\u9a91\u4e58", "\u731b\u64cd", "\u547b\u541f", "\u5a07\u5598", "\u8bf1\u4eba"], "thumbUrl": "https://thumb.tapecontent.net/thumb/8O636L0dvAtooPW/0AM9dVMDaGuD3J.jpg"}, {"name": "\u5c0f\u5b9d\u5bfb\u82b1\u7ea6\u4e86\u4e2a\u725b\u4ed4\u77ed\u88e4\u767d\u8863\u5c11\u5987\uff0c\u6c99\u53d1\u8c03\u60c5\u53e3\u4ea4\u8214\u5976\u4fa7\u5165\u731b\u64cd\u4e0a\u4f4d\u9a91\u4e58\uff0c\u547b\u541f\u5a07\u5598\u975e\u5e38\u8bf1\u4eba", "size": 92647849, "link": "https://streamtape.com/e/m61jwDX4MGIbJZD", "created_at": "2022\u5e7403\u670813\u65e5 08:47:59", "downloads": 0, "linkid": "m61jwDX4MGIbJZD", "convert": "converted", "achorname": "\u4e38\u5b50\u5466", "subscribe": "128.6\u4e07\u4f4d\u8ba2\u9605\u8005", "avatar-img": "https://huyaimg.msstatic.com/avatar/1022/07/ec5fef7c7662720286fbbb12395390_180_135.jpg?1628178596?457957", "folderName": "\u5c0f\u5b9d\u5bfb\u82b1\u7ea6\u4e86\u4e2a\u725b\u4ed4\u77ed\u88e4\u767d\u8863\u5c11\u5987\uff0c\u6c99\u53d1\u8c03\u60c5\u53e3\u4ea4\u8214\u5976\u4fa7\u5165\u731b\u64cd\u4e0a\u4f4d\u9a91\u4e58\uff0c\u547b\u541f\u5a07\u5598\u975e\u5e38\u8bf1\u4eba", "tags": ["\u5c0f\u5b9d", "\u5bfb\u82b1", "\u7ea6", "\u4e86", "\u4e2a", "\u725b\u4ed4", "\u77ed\u88e4", "\u767d\u8863", "\u5c11\u5987", "\uff0c", "\u6c99\u53d1", "\u8c03\u60c5", "\u53e3\u4ea4", "\u8214", "\u5976\u4fa7", "\u5165", "\u731b\u64cd", "\u4e0a\u4f4d", "\u9a91\u4e58", "\uff0c", "\u547b\u541f", "\u5a07\u5598", "\u975e\u5e38", "\u8bf1\u4eba"], "thumbUrl": "https://thumb.tapecontent.net/thumb/m61jwDX4MGIbJZD/08KQZXdODgFbjYz.jpg"}, {"name": "\u5c0f\u5b9d\u5bfb\u82b1\u5927\u795e\u9ad8\u7aef\u5927\u5708\u5916\u56f4\u59b9\u5b50\uff0c\u725b\u4ed4\u77ed\u88e4\u9a91\u5728\u8eab\u4e0a\u820c\u543b\u8c03\u60c5\uff0c\u6df1\u5589\u8214\u5c4c\u6263\u7a74\u9a91\u4e58\u62bd\u63d2\uff0c\u64cd\u7684\u59b9\u5b50\u597d\u723d\u547b\u541f\u8fde\u8fde", "size": 80599879, "link": "https://streamtape.com/e/Y8dOyYav8OHo6z", "created_at": "2022\u5e7403\u670812\u65e5 18:04:52", "downloads": 0, "linkid": "Y8dOyYav8OHo6z", "convert": "converted", "achorname": "\u4e38\u5b50\u5466", "subscribe": "128.6\u4e07\u4f4d\u8ba2\u9605\u8005", "avatar-img": "https://huyaimg.msstatic.com/avatar/1022/07/ec5fef7c7662720286fbbb12395390_180_135.jpg?1628178596?457957", "folderName": "\u5c0f\u5b9d\u5bfb\u82b1\u5927\u795e\u9ad8\u7aef\u5927\u5708\u5916\u56f4\u59b9\u5b50\uff0c\u725b\u4ed4\u77ed\u88e4\u9a91\u5728\u8eab\u4e0a\u820c\u543b\u8c03\u60c5\uff0c\u6df1\u5589\u8214\u5c4c\u6263\u7a74\u9a91\u4e58\u62bd\u63d2\uff0c\u64cd\u7684\u59b9\u5b50\u597d\u723d\u547b\u541f\u8fde\u8fde", "tags": ["\u5c0f\u5b9d", "\u5bfb\u82b1", "\u5927\u795e", "\u9ad8\u7aef", "\u5927", "\u5708", "\u5916\u56f4", "\u59b9\u5b50", "\uff0c", "\u725b\u4ed4", "\u77ed\u88e4", "\u9a91", "\u5728", "\u8eab\u4e0a", "\u820c\u543b", "\u8c03\u60c5", "\uff0c", "\u6df1\u5589", "\u8214", "\u5c4c", "\u6263", "\u7a74", "\u9a91\u4e58", "\u62bd\u63d2", "\uff0c", "\u64cd", "\u7684", "\u59b9\u5b50", "\u597d\u723d", "\u547b\u541f", "\u8fde\u8fde"], "thumbUrl": "https://thumb.tapecontent.net/thumb/Y8dOyYav8OHo6z/XAgqzQkGeaiA6e.jpg"}, {"name": "\u5c0f\u5b9d\u5bfb\u82b1\u4eca\u665a\u7ea6\u4e86\u4e2a\u767d\u8863\u59b9\u5b50TP\u556a\u556a\uff0c\u8e72\u7740\u53e3\u4ea4\u5c11\u5987\u6478\u903c\u8c03\u60c5\u9a91\u4e58\u540e\u5165\u731b\u64cd", "size": 222445287, "link": "https://streamtape.com/e/ZKMXGqmJMLHRvQ", "created_at": "2022\u5e7403\u670813\u65e5 07:55:16", "downloads": 0, "linkid": "ZKMXGqmJMLHRvQ", "convert": "converted", "achorname": "\u4e38\u5b50\u5466", "subscribe": "128.6\u4e07\u4f4d\u8ba2\u9605\u8005", "avatar-img": "https://huyaimg.msstatic.com/avatar/1022/07/ec5fef7c7662720286fbbb12395390_180_135.jpg?1628178596?457957", "folderName": "\u5c0f\u5b9d\u5bfb\u82b1\u4eca\u665a\u7ea6\u4e86\u4e2a\u767d\u8863\u59b9\u5b50TP\u556a\u556a\uff0c\u8e72\u7740\u53e3\u4ea4\u5c11\u5987\u6478\u903c\u8c03\u60c5\u9a91\u4e58\u540e\u5165\u731b\u64cd", "tags": ["\u5c0f\u5b9d", "\u5bfb\u82b1", "\u4eca\u665a", "\u7ea6", "\u4e86", "\u4e2a", "\u767d\u8863", "\u59b9\u5b50", "TP", "\u556a\u556a", "\uff0c", "\u8e72", "\u7740", "\u53e3\u4ea4", "\u5c11\u5987", "\u6478", "\u903c", "\u8c03\u60c5", "\u9a91\u4e58", "\u540e\u5165", "\u731b\u64cd"], "thumbUrl": "https://thumb.tapecontent.net/thumb/ZKMXGqmJMLHRvQ/wV1xm9KvyQfJwkk.jpg"}, {"name": "\u5c0f\u5b9d\u5bfb\u82b1\u7ea6\u4e86\u4e2a\u7ea2\u88d9\u59b9\u5b50TP\u556a\u556a\uff0c\u5750\u5728\u8eab\u4e0a\u6478\u903c\u8214\u5f04\u53e3\u4ea4\u5927\u529b\u731b\u64cd\uff0c\u547b\u541f\u5a07\u5598\u975e\u5e38\u8bf1\u4eba", "size": 122807839, "link": "https://streamtape.com/e/eGoKXZek8dhw8y", "created_at": "2022\u5e7403\u670813\u65e5 08:45:19", "downloads": 0, "linkid": "eGoKXZek8dhw8y", "convert": "converted", "achorname": "\u4e38\u5b50\u5466", "subscribe": "128.6\u4e07\u4f4d\u8ba2\u9605\u8005", "avatar-img": "https://huyaimg.msstatic.com/avatar/1022/07/ec5fef7c7662720286fbbb12395390_180_135.jpg?1628178596?457957", "folderName": "\u5c0f\u5b9d\u5bfb\u82b1\u7ea6\u4e86\u4e2a\u7ea2\u88d9\u59b9\u5b50TP\u556a\u556a\uff0c\u5750\u5728\u8eab\u4e0a\u6478\u903c\u8214\u5f04\u53e3\u4ea4\u5927\u529b\u731b\u64cd\uff0c\u547b\u541f\u5a07\u5598\u975e\u5e38\u8bf1\u4eba", "tags": ["\u5c0f\u5b9d", "\u5bfb\u82b1", "\u7ea6", "\u4e86", "\u4e2a", "\u7ea2\u88d9", "\u59b9\u5b50", "TP", "\u556a\u556a", "\uff0c", "\u5750\u5728", "\u8eab\u4e0a", "\u6478", "\u903c", "\u8214", "\u5f04\u53e3", "\u4ea4", "\u5927\u529b", "\u731b\u64cd", "\uff0c", "\u547b\u541f", "\u5a07\u5598", "\u975e\u5e38", "\u8bf1\u4eba"], "thumbUrl": "https://thumb.tapecontent.net/thumb/eGoKXZek8dhw8y/Mxea1vgRD7TmOJ1.jpg"}, {"name": "\u5c0f\u5b9d\u5bfb\u82b1\u5927\u795e\u63a2\u82b1\u9ad8\u7d20\u8d28\u5916\u56f4\uff0c\u82d7\u6761\u8eab\u6750\u957f\u817f\u59b9\u5b50\uff0c\u8e72\u7740\u53e3\u4ea4\u8214\u5c4c\u62ac\u817f\u62bd\u63d2\uff0c\u4e0a\u4f4d\u9a91\u4e58\u540e\u5165\u5927\u529b\u649e\u51fb", "size": 90974094, "link": "https://streamtape.com/e/gaxr8ve0QoCqjkz", "created_at": "2022\u5e7403\u670813\u65e5 09:27:50", "downloads": 0, "linkid": "gaxr8ve0QoCqjkz", "convert": "converted", "achorname": "\u4e38\u5b50\u5466", "subscribe": "128.6\u4e07\u4f4d\u8ba2\u9605\u8005", "avatar-img": "https://huyaimg.msstatic.com/avatar/1022/07/ec5fef7c7662720286fbbb12395390_180_135.jpg?1628178596?457957", "folderName": "\u5c0f\u5b9d\u5bfb\u82b1\u5927\u795e\u63a2\u82b1\u9ad8\u7d20\u8d28\u5916\u56f4\uff0c\u82d7\u6761\u8eab\u6750\u957f\u817f\u59b9\u5b50\uff0c\u8e72\u7740\u53e3\u4ea4\u8214\u5c4c\u62ac\u817f\u62bd\u63d2\uff0c\u4e0a\u4f4d\u9a91\u4e58\u540e\u5165\u5927\u529b\u649e\u51fb", "tags": ["\u5c0f\u5b9d", "\u5bfb\u82b1", "\u5927\u795e", "\u63a2\u82b1", "\u9ad8\u7d20\u8d28", "\u5916\u56f4", "\uff0c", "\u82d7\u6761\u8eab\u6750", "\u957f\u817f", "\u59b9\u5b50", "\uff0c", "\u8e72", "\u7740", "\u53e3\u4ea4", "\u8214", "\u5c4c", "\u62ac\u817f", "\u62bd\u63d2", "\uff0c", "\u4e0a\u4f4d", "\u9a91\u4e58", "\u540e\u5165", "\u5927\u529b", "\u649e\u51fb"], "thumbUrl": "https://thumb.tapecontent.net/thumb/gaxr8ve0QoCqjkz/R49dQKr21DSdgy9.jpg"}, {"name": "\u5c0f\u5b9d\u5bfb\u82b1\u7b2c\u4e8c\u573a\u767d\u8863\u5927\u957f\u817f\u6027\u611f\u59b9\u5b50\uff0c\u820c\u543b\u8c03\u60c5\u4e92\u647869\u53e3\u4ea4\u7279\u5199\u53e3\u903c\uff0c\u4e0a\u4f4d\u9a91\u5750\u62bd\u63d2\u731b\u64cd\u547b\u541f", "size": 94256387, "link": "https://streamtape.com/e/69BZjlm44gC97zr", "created_at": "2022\u5e7403\u670813\u65e5 08:30:41", "downloads": 0, "linkid": "69BZjlm44gC97zr", "convert": "converted", "achorname": "\u4e38\u5b50\u5466", "subscribe": "128.6\u4e07\u4f4d\u8ba2\u9605\u8005", "avatar-img": "https://huyaimg.msstatic.com/avatar/1022/07/ec5fef7c7662720286fbbb12395390_180_135.jpg?1628178596?457957", "folderName": "\u5c0f\u5b9d\u5bfb\u82b1\u7b2c\u4e8c\u573a\u767d\u8863\u5927\u957f\u817f\u6027\u611f\u59b9\u5b50\uff0c\u820c\u543b\u8c03\u60c5\u4e92\u647869\u53e3\u4ea4\u7279\u5199\u53e3\u903c\uff0c\u4e0a\u4f4d\u9a91\u5750\u62bd\u63d2\u731b\u64cd\u547b\u541f", "tags": ["\u5c0f\u5b9d", "\u5bfb\u82b1", "\u7b2c\u4e8c\u573a", "\u767d\u8863", "\u5927\u957f", "\u817f", "\u6027\u611f", "\u59b9\u5b50", "\uff0c", "\u820c\u543b", "\u8c03\u60c5", "\u4e92\u6478", "69", "\u53e3\u4ea4", "\u7279\u5199", "\u53e3", "\u903c", "\uff0c", "\u4e0a\u4f4d", "\u9a91\u5750", "\u62bd\u63d2", "\u731b\u64cd", "\u547b\u541f"], "thumbUrl": "https://thumb.tapecontent.net/thumb/69BZjlm44gC97zr/lPyloZelJrS73Mm.jpg"}, {"name": "\u5229\u54e5\u5bfb\u82b112-05\u767d\u8863\u7f8e\u5973", "size": 231663787, "link": "https://streamtape.com/e/YKqalqlaB8Iv9VZ", "created_at": "2022\u5e7403\u670813\u65e5 19:13:41", "downloads": 0, "linkid": "YKqalqlaB8Iv9VZ", "convert": "converted", "achorname": "\u4e38\u5b50\u5466", "subscribe": "128.6\u4e07\u4f4d\u8ba2\u9605\u8005", "avatar-img": "https://huyaimg.msstatic.com/avatar/1022/07/ec5fef7c7662720286fbbb12395390_180_135.jpg?1628178596?457957", "folderName": "\u5229\u54e5\u5bfb\u82b112-05\u767d\u8863\u7f8e\u5973", "tags": ["\u5229\u54e5", "\u5bfb\u82b1", "12", "-", "05", "\u767d\u8863", "\u7f8e\u5973"], "thumbUrl": "https://thumb.tapecontent.net/thumb/YKqalqlaB8Iv9VZ/0AL2DlyQaPHbRQx.jpg"}, {"name": "\u5c0f\u5b9d\u5bfb\u82b1\u7ea6\u4e86\u4e2a\u767d\u8863\u4e38\u5b50\u5934\u751c\u7f8e\u840c\u59b9\u556a\u556a\uff0c\u820c\u543b\u4e92\u8214\u8c03\u60c5\u53e3\u4ea4\u9a91\u4e58\u62b1\u7740\u731b\u64cd", "size": 166441185, "link": "https://streamtape.com/e/4mlMepq4wKIKoz2", "created_at": "2022\u5e7403\u670813\u65e5 05:50:16", "downloads": 0, "linkid": "4mlMepq4wKIKoz2", "convert": "converted", "achorname": "\u4e38\u5b50\u5466", "subscribe": "128.6\u4e07\u4f4d\u8ba2\u9605\u8005", "avatar-img": "https://huyaimg.msstatic.com/avatar/1022/07/ec5fef7c7662720286fbbb12395390_180_135.jpg?1628178596?457957", "folderName": "\u5c0f\u5b9d\u5bfb\u82b1\u7ea6\u4e86\u4e2a\u767d\u8863\u4e38\u5b50\u5934\u751c\u7f8e\u840c\u59b9\u556a\u556a\uff0c\u820c\u543b\u4e92\u8214\u8c03\u60c5\u53e3\u4ea4\u9a91\u4e58\u62b1\u7740\u731b\u64cd", "tags": ["\u5c0f\u5b9d", "\u5bfb\u82b1", "\u7ea6", "\u4e86", "\u4e2a", "\u767d\u8863", "\u4e38\u5b50", "\u5934", "\u751c\u7f8e", "\u840c\u59b9", "\u556a\u556a", "\uff0c", "\u820c", "\u543b", "\u4e92", "\u8214", "\u8c03\u60c5", "\u53e3\u4ea4", "\u9a91\u4e58", "\u62b1", "\u7740", "\u731b\u64cd"], "thumbUrl": "https://thumb.tapecontent.net/thumb/4mlMepq4wKIKoz2/vkkgkgK2Wgs41m7.jpg"}, {"name": "\u3010AI\u9ad8\u6e05\u753b\u8d282K\u4fee\u590d\u3011\u5c0f\u5b9d\u5bfb\u82b1\u6781\u54c1\u9ad8\u8d28\u91cf\u725b\u4ed4\u88e4\u5916\u56f4\u59b9\u5b50\uff0c\u5750\u5728\u8eab\u4e0a\u8c03\u60c5\u4e00\u756a\u820c\u543b\u6478\u5976\uff0c\u4e0a\u4f4d\u81ea\u5df1\u52a8\u5927\u529b\u731b\u64cd", "size": 197562344, "link": "https://streamtape.com/e/Wb3kmBzqOgsbOdG", "created_at": "2022\u5e7403\u670813\u65e5 10:19:53", "downloads": 0, "linkid": "Wb3kmBzqOgsbOdG", "convert": "converted", "achorname": "\u4e38\u5b50\u5466", "subscribe": "128.6\u4e07\u4f4d\u8ba2\u9605\u8005", "avatar-img": "https://huyaimg.msstatic.com/avatar/1022/07/ec5fef7c7662720286fbbb12395390_180_135.jpg?1628178596?457957", "folderName": "\u3010AI\u9ad8\u6e05\u753b\u8d282K\u4fee\u590d\u3011\u5c0f\u5b9d\u5bfb\u82b1\u6781\u54c1\u9ad8\u8d28\u91cf\u725b\u4ed4\u88e4\u5916\u56f4\u59b9\u5b50\uff0c\u5750\u5728\u8eab\u4e0a\u8c03\u60c5\u4e00\u756a\u820c\u543b\u6478\u5976\uff0c\u4e0a\u4f4d\u81ea\u5df1\u52a8\u5927\u529b\u731b\u64cd", "tags": ["\u3010", "AI", "\u9ad8\u6e05", "\u753b\u8d28", "2K", "\u4fee\u590d", "\u3011", "\u5c0f\u5b9d", "\u5bfb\u82b1", "\u6781\u54c1", "\u9ad8\u8d28\u91cf", "\u725b\u4ed4\u88e4", "\u5916\u56f4", "\u59b9\u5b50", "\uff0c", "\u5750\u5728", "\u8eab\u4e0a", "\u8c03\u60c5", "\u4e00\u756a", "\u820c\u543b", "\u6478\u5976", "\uff0c", "\u4e0a\u4f4d", "\u81ea\u5df1", "\u52a8", "\u5927\u529b", "\u731b\u64cd"], "thumbUrl": "https://thumb.tapecontent.net/thumb/Wb3kmBzqOgsbOdG/M9bbWGeWKlumXej.jpg"}, {"name": "\u5c0f\u5b9d\u5bfb\u82b1\u5305\u81c0\u88d9\u6027\u611f\u7f8e\u4e73\u840c\u59b9\u5b50\uff0c\u820c\u543b\u4e92\u6478\u8c03\u60c5\u955c\u5934\u524d\u7279\u5199\u53e3\u4ea4\uff0c\u540e\u5165\u62bd\u63d2\u731b\u64cd\u6b22\u52a8\u5976\u5b50", "size": 107180756, "link": "https://streamtape.com/e/ygYKYpwxJJs1QBZ", "created_at": "2022\u5e7403\u670813\u65e5 08:33:04", "downloads": 0, "linkid": "ygYKYpwxJJs1QBZ", "convert": "converted", "achorname": "\u4e38\u5b50\u5466", "subscribe": "128.6\u4e07\u4f4d\u8ba2\u9605\u8005", "avatar-img": "https://huyaimg.msstatic.com/avatar/1022/07/ec5fef7c7662720286fbbb12395390_180_135.jpg?1628178596?457957", "folderName": "\u5c0f\u5b9d\u5bfb\u82b1\u5305\u81c0\u88d9\u6027\u611f\u7f8e\u4e73\u840c\u59b9\u5b50\uff0c\u820c\u543b\u4e92\u6478\u8c03\u60c5\u955c\u5934\u524d\u7279\u5199\u53e3\u4ea4\uff0c\u540e\u5165\u62bd\u63d2\u731b\u64cd\u6b22\u52a8\u5976\u5b50", "tags": ["\u5c0f\u5b9d", "\u5bfb\u82b1", "\u5305", "\u81c0", "\u88d9", "\u6027\u611f\u7f8e", "\u4e73\u840c", "\u59b9\u5b50", "\uff0c", "\u820c\u543b", "\u4e92\u6478", "\u8c03\u60c5", "\u955c\u5934", "\u524d", "\u7279\u5199", "\u53e3\u4ea4", "\uff0c", "\u540e\u5165", "\u62bd\u63d2", "\u731b\u64cd", "\u6b22\u52a8", "\u5976\u5b50"], "thumbUrl": "https://thumb.tapecontent.net/thumb/ygYKYpwxJJs1QBZ/xgmZLpoVJMfkJ8P.jpg"}, {"name": "\u5c0f\u5b9d\u5bfb\u82b1\u7ea6\u4e86\u4e2a\u77ed\u53d1\u767d\u8863\u751c\u7f8e\u840c\u59b9\u556a\u556a\uff0c\u6c99\u53d1\u4e0a\u8c03\u60c5\u53e3\u4ea4\u63b0\u7a74\u6478\u903c\u9a91\u4e58\u731b\u64cd", "size": 174118409, "link": "https://streamtape.com/e/DPzk2DadXKTB00", "created_at": "2022\u5e7403\u670813\u65e5 07:51:07", "downloads": 0, "linkid": "DPzk2DadXKTB00", "convert": "converted", "achorname": "\u4e38\u5b50\u5466", "subscribe": "128.6\u4e07\u4f4d\u8ba2\u9605\u8005", "avatar-img": "https://huyaimg.msstatic.com/avatar/1022/07/ec5fef7c7662720286fbbb12395390_180_135.jpg?1628178596?457957", "folderName": "\u5c0f\u5b9d\u5bfb\u82b1\u7ea6\u4e86\u4e2a\u77ed\u53d1\u767d\u8863\u751c\u7f8e\u840c\u59b9\u556a\u556a\uff0c\u6c99\u53d1\u4e0a\u8c03\u60c5\u53e3\u4ea4\u63b0\u7a74\u6478\u903c\u9a91\u4e58\u731b\u64cd", "tags": ["\u5c0f\u5b9d", "\u5bfb\u82b1", "\u7ea6", "\u4e86", "\u4e2a", "\u77ed\u53d1", "\u767d\u8863", "\u751c\u7f8e", "\u840c\u59b9", "\u556a\u556a", "\uff0c", "\u6c99\u53d1", "\u4e0a", "\u8c03\u60c5", "\u53e3\u4ea4", "\u63b0", "\u7a74", "\u6478", "\u903c", "\u9a91\u4e58", "\u731b\u64cd"], "thumbUrl": "https://thumb.tapecontent.net/thumb/DPzk2DadXKTB00/dRzaxGkKl1ugGB.jpg"}]